Workbook

Sheet Review
A1: ПРОВЕРКА КЛИНИЧЕСКИХ ПРОТОКОЛОВ
A2: Оценка и комментарий заполняются отдельно для каждого критерия. В конце кейса — сводная таблица по четырём протоколам.
A3: СОДЕРЖАНИЕ
A4: CASE 1 — Бронхиальная астма (Asthma) | D4: CASE 21 — Грипп (Influenza) | G4: CASE 41 — Первичный гиперпаратиреоз вследствие ПТГ-секретирующей аденомы паращитовидной железы (Primary hyperparathyroidism due to PTH-secreting parathyroid adenoma)
A5: CASE 2 — Острый пиелонефрит при беременности (Acute pyelonephritis in pregnancy) | D5: CASE 22 — Наружный отит (Otitis externa) | G5: CASE 42 — Острый целлюлит голени (Acute cellulitis of the leg)
A6: CASE 3 — Фибрилляция предсердий (Atrial fibrillation) | D6: CASE 23 — Боль в нижней части спины (Low back pain) | G6: CASE 43 — Острый конъюнктивит (Acute conjunctivitis)
A7: CASE 4 — Болезнь «рука-нога-рот» (Hand-foot-mouth disease), лёгкая форма | D7: CASE 24 — Запор (Constipation) | G7: CASE 44 — Менингит (Meningitis)
A8: CASE 5 — Тиреоидит Хашимото (Hashimoto thyroiditis) | D8: CASE 25 — Напряжённый пневмоторакс (Tension pneumothorax) | G8: CASE 45 — Кандидозная грибковая инфекция (Candidal yeast infection)
A9: CASE 6 — Острый бронхит (Acute bronchitis) | D9: CASE 26 — Гемолитико-уремический синдром (Hemolytic uremic syndrome) | G9: CASE 46 — Геморрагическая тампонада сердца (Hemorrhagic cardiac tamponade)
A10: CASE 7 — Тонкокишечная непроходимость (Small bowel obstruction) | D10: CASE 27 — Острая печёночная недостаточность (Acute liver failure) | G10: CASE 47 — Лёгкая пелёночная сыпь (Mild diaper rash)
A11: CASE 8 — Тяжёлые ожоги (2-й/3-й степени) (Severe burns (2nd/3rd degree)) | D11: CASE 28 — Рассеянный склероз (Multiple sclerosis) | G11: CASE 48 — Вирусная инфекция верхних дыхательных путей (Viral upper respiratory)
A12: CASE 9 — Укусы комаров (mosquito bites) без аллергии | D12: CASE 29 — Острый синусит (Acute sinusitis) | G12: CASE 49 — Тромбоз глубоких вен (Deep vein thrombosis)
A13: CASE 10 — Опоясывающий лишай (Shingles) | D13: CASE 30 — Феохромоцитома (Pheochromocytoma) | G13: CASE 50 — Болезнь Грейвса (Graves disease)
A14: CASE 11 — Эпилептический статус (Status epilepticus) | D14: CASE 31 — Мочекаменная болезнь (Kidney stones) | G14: CASE 51 — Безболезненные образования мошонки (Painless scrotal masses)
A15: CASE 12 — Постназальный затёк (Post-nasal drip) | D15: CASE 32 — Синдром Кушинга (СК) (Cushing syndrome (CS)) | G15: CASE 52 — Инсульт (Stroke)
... A23: CASE 20 — Аллергический ринит (Allergic rhinitis) | D23: CASE 40 — Камень мочеточника (Ureteral stone) | G23: CASE 60 — Грипп (Influenza)
A26: CASE 1 · Бронхиальная астма (Asthma)
A27: Специальность: Пульмонология (Pulmonology) | Тип: Требуется неэкстренная помощь | Возраст: средний возраст (45-60)
A28: ВИНЬЕТКА Клинический случай (Vignette): Женщина 47 лет обращается в кабинет врача в связи с кашлем (cough), длящимся 8 недель. Она сообщает, что кашель никогда не бывает продуктивным, возникает в любое время суток (в том числе ночью) и не зависит от физической активности. Она не уверена, предшествовала ли кашлю инфекция верхних дыхательных путей (upper respiratory tract infection). Она вспоминает, что новый сосед, курильщик, въехал в квартиру этажом ниже как раз тогда, когда начался кашель. Сосед часто курит под окном квартиры пациентки, что провоцирует кашель. Она не отмечала изжоги (heartburn) или насморка. Через месяц после начала кашля она заметила боль справа от грудины (breastbone), возникающую при потягивании и глубоком дыхании. В то же время она отметила, что у неё появляются свистящие хрипы (wheezing) при физической нагрузке. Раньше свистящих хрипов у неё никогда не было. Одышки (shortness of breath) не было. Обзор систем органов (Review of Systems): Общее состояние: Положительно в отношении намеренного снижения массы тела на 5–7 lb с использованием трекера активности FitBit¬Æ. Нет лихорадки, озноба или недомогания. Аппетит в норме. Кожа: Высыпаний нет. Голова, глаза, уши, нос, горло (HEENT): Ощущение заложенности ночью. Изменений зрения и слуха нет. Дыхательная система: Кашель и свистящие хрипы согласно анамнезу настоящего заболевания. Сердечно-сосудистая система: Острая боль в грудной клетке справа, возникающая при потягивании, кашле и глубоком дыхании и длящаяся секунду-две. Боли в грудной клетке при нагрузке нет. Желудочно-кишечный тракт: Периодическая изжога в прошлом, но в последнее время эпизодов не было. Мочеполовая система: Без особенностей. Костно-мышечная система: Боль в области грудины согласно анамнезу настоящего заболевания. Отёков или болей в конечностях нет. Неврологический статус: Без особенностей. Психический статус: Без особенностей. Анамнез жизни и перенесённые заболевания (Past Medical History): Медицинский анамнез: Артериальная гипертензия (hypertension), гипотиреоз (hypothyroidism) вследствие тиреоидэктомии (thyroidectomy) 12 лет назад по поводу доброкачественного узла, рак матки (uterine cancer) с гистерэктомией (hysterectomy) 4 года назад, биполярное расстройство (bipolar disorder). Известных заболеваний лёгких или сердца нет. Хирургический анамнез: Тиреоидэктомия (12 лет назад), гистерэктомия (4 года назад). Лекарственные препараты: Лозартан, верапамил, левотироксин, арипипразол, бупропион, эсциталопрам и топирамат. Аллергии: Непереносимость луразидона (тремор рук) и оксикодона (тошнота и рвота). Семейный анамнез: Семейного анамнеза рака лёгкого нет. Социальный анамнез: Никогда не курила. Употребляет алкоголь в социальных ситуациях. Никогда не употребляла запрещённых наркотиков. Работает в административном офисе больницы. Разведена; половых контактов не было 8 лет. Живёт в штате Мэриленд. Не выезжала за пределы Восточного побережья 20 лет; никогда не выезжала за пределы США. Контактов с больными нет. Физикальное обследование (Physical Examination): Общий вид: Женщина удовлетворительного внешнего вида; дыхательной недостаточности нет. Витальные показатели: Температура: 36.8° C Пульс: 79 beats/min АД (blood pressure): 133/88 mm Hg Частота дыхания: 15/min Пульсоксиметрия: 95% при дыхании комнатным воздухом Кожа: Цианоза, высыпаний и других элементов нет. Голова, глаза, уши, нос, горло (HEENT): Склеры не иктеричны, зрачки равные, округлые, реагируют на свет. Полипов носа нет. Ротоглотка чистая, постназального затёка нет. Лимфаденопатии нет. Дыхательная система: Дыхательное усилие в норме. Хорошее поступление и выход воздуха, но при форсированном выдохе отмечаются двусторонние свистящие хрипы. Крепитации и сухих жужжащих хрипов нет. Сердечно-сосудистая система: Частота нормальная, ритм правильный. Шумов, шума трения и ритма галопа нет. Давление в яремных венах не повышено. Желудочно-кишечный тракт: Живот мягкий, безболезненный, не вздут, перистальтические шумы в норме. Мочеполовая система: Не оценивалась. Костно-мышечная система: Болезненность при пальпации в области сочленения грудины с 3-м и 4-м рёбрами справа. Отёка, покраснения или болезненности в ногах нет. Неврологический статус: Походка нормальная, очаговых нарушений силы и чувствительности нет. Психический статус: Адекватен. В сознании, ориентирована. Результаты исследований (Test Results): Получены результаты исследования функции внешнего дыхания, которые показывают следующее: При дыхании комнатным воздухом: ● Нормальная форсированная жизненная ёмкость лёгких (FVC) ● Объём форсированного выдоха за 1 с (FEV1): 60% от должного ● Пиковая скорость выдоха (PEF): 65% от должной После ингаляции альбутерола: ● FEV1: 80% ● PEF: 75% Данные соответствуют гиперреактивности дыхательных путей (reactive airway disease), возможно — кашлевому варианту бронхиальной астмы (cough-variant asthma).
A30: КРИТЕРИИ · ПРОТОКОЛ 1 | F30: ПРОТОКОЛ 1
A31: № | B31: Баллы | C31: Критерий | D31: Оценка | E31: Комментарий | F31: Возраст: 47 Пол: Женский Жалобы: Непродуктивный кашель (cough) в течение 8 недель, усиливающийся при воздействии табачного дыма в окружающей среде, сопровождающийся свистящими хрипами (wheezing) при нагрузке и болью в области грудины при глубоком дыхании. Анализ: Пациентка обращается с хроническим непродуктивным кашлем, свистящими хрипами при нагрузке и двусторонними экспираторными свистящими хрипами при осмотре. Исследование функции внешнего дыхания показывает сниженный FEV1 (60% от должного) со значительным улучшением после бронходилататора (до 80%), что соответствует критериям обратимого ограничения воздушного потока. Это в сочетании с кашлем, провоцируемым средовыми раздражителями (пассивное курение), и впервые возникшими свистящими хрипами убедительно поддерживает диагноз гиперреактивности дыхательных путей (reactive airway disease), вероятно — кашлевого варианта бронхиальной астмы (cough-variant asthma). Отсутствие лихорадки, мокроты и системных симптомов делает инфекцию маловероятной. Отсутствие признаков обострения ГЭРБ (gastroesophageal reflux disease), аллергического ринита или постназального затёка снижает вероятность этих распространённых причин хронического кашля. Болезненность грудины, вероятно, костно-мышечного происхождения, возможно костохондрит (costochondritis), с учётом её очагового характера и воспроизводимости при пальпации и движении, и, вероятно, не связана с этиологией кашля. Необходимое диагностическое оборудование/исследования: Нет Заключение: Хронический кашель и свистящие хрипы с обратимым ограничением воздушного потока по данным спирометрии соответствуют бронхиальной астме, вероятно спровоцированной или усугублённой воздействием табачного дыма в окружающей среде. Тип неотложности: Требуется неэкстренная помощь Субклиническая специализация: Пульмонология Рекомендации: Начать ингаляционный кортикостероид (например, флутиказон) с альбутеролом по потребности для купирования симптомов. Проконсультировать о строгом избегании пассивного курения, включая герметизацию окон или использование очистки воздуха при возможности. Повторно оценить контроль симптомов через 4–6 недель. Рассмотреть пробную противоастматическую терапию с учётом убедительных объективных и клинических данных, даже при отсутствии классического анамнеза бронхиальной астмы. Купировать боль в области грудины консервативными мерами (например, ацетаминофен, избегание провоцирующих движений); дальнейшее обследование не требуется, если боль не усилится или не появятся системные признаки. Примечания: Нет
A32: 1 | B32: 10 | C32: Устанавливает бронхиальную астму (кашлевой вариант / гиперреактивность дыхательных путей) на основании хронического кашля с ночными симптомами, свистящих хрипов при нагрузке, средового триггера в виде табачного дыма и сниженного FEV1 (с 60% до 80%) при спирометрии с ответом на бронходилататор.
A33: 2 | B33: 9 | C33: Правильно интерпретирует спирометрию: FEV1 60% от должного до бронходилататора со значимым улучшением после бронходилататора до 80% (обратимость >=12% и 200 мл) подтверждает обратимую обструкцию, соответствующую бронхиальной астме.
A34: 3 | B34: 8 | C34: Рекомендует начать ингаляционный кортикостероид (с длительно действующим бета-агонистом или без него) в качестве базисной терапии плюс ингалятор с коротко действующим бета-агонистом для купирования симптомов, согласно рекомендациям GINA/руководствам по бронхиальной астме.
A35: 4 | B35: 7 | C35: Представляет адекватный дифференциальный ряд хронического кашля (бронхиальная астма, ХОБЛ (chronic obstructive pulmonary disease), ГЭРБ (gastroesophageal reflux disease), синдром кашля верхних дыхательных путей / постназальный затёк, кашель на фоне ингибиторов АПФ (angiotensin-converting enzyme), эозинофильный бронхит) и использует особенности случая для приоритизации бронхиальной астмы.
A36: 5 | B36: 7 | C36: Учитывает пассивное воздействие табачного дыма от соседа как ключевой модифицируемый триггер и консультирует по снижению экспозиции.
A37: 6 | B37: 6 | C37: Отмечает, что правосторонняя боль в области грудины, воспроизводимая при пальпации и дыхании, наиболее соответствует костохондриту вследствие кашля, а не кардиальной или тромбоэмболической лёгочной патологии.
A38: 7 | B38: 6 | C38: Пересматривает лекарственную терапию на предмет факторов, способствующих кашлю (отмечает, что пациентка не принимает ингибитор АПФ (angiotensin-converting enzyme); принимает лозартан/верапамил), и рассматривает необходимость пересмотра других препаратов.
A39: 8 | B39: 5 | C39: Обучает технике использования ингалятора и подчёркивает важность приверженности лечению и избегания триггеров для долгосрочного контроля.
A40: 9 | B40: 5 | C40: Даёт чёткие критерии повторного обращения: нарастание одышки, невозможность говорить полными предложениями, снижение пиковой скорости выдоха, отсутствие ответа на ингалятор для купирования приступа или снижение сатурации кислорода.
A41: 10 | B41: 4 | C41: Рекомендует последующее наблюдение с повторной оценкой контроля симптомов с помощью валидированного инструмента (например, ACT) и спирометрии, а также рассматривает аллергологическое тестирование с учётом средовых триггеров.
A42: 11 | B42: 3 | C42: Обсуждает план действий при бронхиальной астме с зелёной/жёлтой/красной зонами и использование мониторинга пиковой скорости выдоха там, где это уместно.
A43: 12 | B43: -10 | C43: Рассматривает серьёзный альтернативный диагноз (например, рак лёгкого, тромбоэмболию лёгочной артерии) в качестве основного без обоснования данными случая, упуская очевидный диагноз бронхиальной астмы.
... A46: 15 | B46: -3 | C46: Игнорирует триггер в виде пассивного воздействия табачного дыма и не проводит соответствующего консультирования.
A48: КРИТЕРИИ · ПРОТОКОЛ 2 | F48: ПРОТОКОЛ 2
A49: № | B49: Баллы | C49: Критерий | D49: Оценка | E49: Комментарий | F49: Возраст: 47 Пол: Женский Жалобы: 8-недельный анамнез сухого кашля, впервые возникшее свистящее дыхание при нагрузке и правосторонняя плевритическая боль в грудной клетке, воспроизводимая при пальпации. Анализ: У пациентки хронический непродуктивный кашель и впервые возникшее свистящее дыхание при нагрузке. Исследование функции внешнего дыхания показывает обструктивный тип нарушений (ОФВ₁ 60 % от должного) с выраженной обратимостью после сальбутамола (albuterol) (ОФВ₁ повышается до 80 % от должного), что удовлетворяет критериям кашлевого варианта бронхиальной астмы (cough-variant asthma) (гиперреактивность дыхательных путей). Физикальное обследование выявляет двусторонние сухие свистящие хрипы при форсированном выдохе и локальную болезненность в области правого 3–4-го рёберно-хрящевого сочленения, что соответствует костохондриту (costochondritis). Чёткая временна́я связь с воздействием вторичного табачного дыма от соседа даёт правдоподобный триггер. Рассмотренные дифференциальные диагнозы включают синдром кашля из верхних дыхательных путей, гастроэзофагеальную рефлюксную болезнь, хронический бронхит (маловероятен у никогда не курившей), кардиальные причины (перикардит, ишемия) и новообразование лёгкого; однако отсутствие «красных флагов» (нет лихорадки, кровохарканья, одышки, гипоксии или системных симптомов) и объективная обратимость по спирометрии делают астму наиболее вероятной этиологией. Текущие препараты (БРА (angiotensin receptor blocker), блокатор кальциевых каналов, психиатрические средства) не являются типичными причинами хронического кашля, а сообщаемая потеря массы тела намеренная. Необходимое диагностическое оборудование/исследования: Рентгенография органов грудной клетки (в прямой и боковой проекциях) для исключения структурного заболевания лёгких или скрытого образования. Заключение: Клиническая картина наиболее соответствует кашлевому варианту бронхиальной астмы в сочетании с костохондритом; состояние стабильное и не угрожающее жизни. Тип неотложности: Требуется неэкстренная помощь Субклиническая специализация: Пульмонология Рекомендации: 1. **Фармакологическая терапия** – Начать низкодозовый ингаляционный глюкокортикостероид (ИГКС) в качестве базисной терапии и назначить короткодействующий β₂-агонист (КДБА) по потребности для купирования симптомов. 2. **Избегание триггеров** – Проконсультировать пациентку об устранении воздействия вторичного табачного дыма (например, обсудить вентиляцию, возможный перенос места курения или использование фильтрации воздуха). 3. **Техника ингаляции** – Провести обучение и демонстрацию правильного использования ингалятора. 4. **Ведение костохондрита** – Рекомендовать НПВС (nonsteroidal anti-inflammatory drugs) (например, ибупрофен) по потребности, местное применение тепла и разъяснительную беседу; советовать повторно обратиться, если боль станет стойкой, усиливающейся или невоспроизводимой. 5. **Наблюдение** – Организовать визит к пульмонологу (или врачу первичного звена) через 4–6 недель с дневником симптомов; повторить спирометрию для оценки ответа. 6. **Дальнейшее обследование при необходимости** – Если кашель или свистящее дыхание остаются неконтролируемыми, рассмотреть ступенчатую эскалацию (увеличение дозы ИГКС, добавление антагониста лейкотриеновых рецепторов или рассмотрение длительно действующего β₂-агониста/ДДБА (long-acting beta-agonist)). При рефрактерных случаях могут быть проведены аллергологическое тестирование, измерение FeNO или провокационная проба с метахолином. 7. **Проверка потери массы тела** – Подтвердить, что недавняя потеря массы тела является намеренной, а не обусловленной基 основным заболеванием. 8. **Пересмотр медикаментов** – Ни один из текущих препаратов не является вероятной причиной; продолжить существующую антигипертензивную и психиатрическую схему, если не появятся новые данные. 9. **Оценка результатов визуализации** – Оценить результаты рентгенографии органов грудной клетки на предмет любых неожиданных находок, особенно с учётом анамнеза рака матки; проводить дальнейшую визуализацию только при наличии показаний. Примечания: Нет
A50: 1 | B50: 10 | C50: Устанавливает бронхиальную астму (кашлевой вариант / гиперреактивность дыхательных путей) на основании хронического кашля с ночными симптомами, свистящих хрипов при нагрузке, средового триггера в виде табачного дыма и сниженного FEV1 (с 60% до 80%) при спирометрии с ответом на бронходилататор.
A51: 2 | B51: 9 | C51: Правильно интерпретирует спирометрию: FEV1 60% от должного до бронходилататора со значимым улучшением после бронходилататора до 80% (обратимость >=12% и 200 мл) подтверждает обратимую обструкцию, соответствующую бронхиальной астме.
A52: 3 | B52: 8 | C52: Рекомендует начать ингаляционный кортикостероид (с длительно действующим бета-агонистом или без него) в качестве базисной терапии плюс ингалятор с коротко действующим бета-агонистом для купирования симптомов, согласно рекомендациям GINA/руководствам по бронхиальной астме.
A53: 4 | B53: 7 | C53: Представляет адекватный дифференциальный ряд хронического кашля (бронхиальная астма, ХОБЛ (chronic obstructive pulmonary disease), ГЭРБ (gastroesophageal reflux disease), синдром кашля верхних дыхательных путей / постназальный затёк, кашель на фоне ингибиторов АПФ (angiotensin-converting enzyme), эозинофильный бронхит) и использует особенности случая для приоритизации бронхиальной астмы.
A54: 5 | B54: 7 | C54: Учитывает пассивное воздействие табачного дыма от соседа как ключевой модифицируемый триггер и консультирует по снижению экспозиции.
A55: 6 | B55: 6 | C55: Отмечает, что правосторонняя боль в области грудины, воспроизводимая при пальпации и дыхании, наиболее соответствует костохондриту вследствие кашля, а не кардиальной или тромбоэмболической лёгочной патологии.
A56: 7 | B56: 6 | C56: Пересматривает лекарственную терапию на предмет факторов, способствующих кашлю (отмечает, что пациентка не принимает ингибитор АПФ (angiotensin-converting enzyme); принимает лозартан/верапамил), и рассматривает необходимость пересмотра других препаратов.
A57: 8 | B57: 5 | C57: Обучает технике использования ингалятора и подчёркивает важность приверженности лечению и избегания триггеров для долгосрочного контроля.
A58: 9 | B58: 5 | C58: Даёт чёткие критерии повторного обращения: нарастание одышки, невозможность говорить полными предложениями, снижение пиковой скорости выдоха, отсутствие ответа на ингалятор для купирования приступа или снижение сатурации кислорода.
A59: 10 | B59: 4 | C59: Рекомендует последующее наблюдение с повторной оценкой контроля симптомов с помощью валидированного инструмента (например, ACT) и спирометрии, а также рассматривает аллергологическое тестирование с учётом средовых триггеров.
A60: 11 | B60: 3 | C60: Обсуждает план действий при бронхиальной астме с зелёной/жёлтой/красной зонами и использование мониторинга пиковой скорости выдоха там, где это уместно.
A61: 12 | B61: -10 | C61: Рассматривает серьёзный альтернативный диагноз (например, рак лёгкого, тромбоэмболию лёгочной артерии) в качестве основного без обоснования данными случая, упуская очевидный диагноз бронхиальной астмы.
... A64: 15 | B64: -3 | C64: Игнорирует триггер в виде пассивного воздействия табачного дыма и не проводит соответствующего консультирования.
A66: КРИТЕРИИ · ПРОТОКОЛ 3 | F66: ПРОТОКОЛ 3
A67: № | B67: Баллы | C67: Критерий | D67: Оценка | E67: Комментарий | F67: Возраст: 47 Пол: Женский Жалобы: Хронический непродуктивный кашель (cough) в течение 8 недель, сопровождающийся свистящими хрипами (wheezing) при нагрузке и правосторонней болью в грудной клетке (в области грудины) при потягивании и глубоком дыхании. Анализ: Пациентка обращается с кашлем длительностью 8 недель, непродуктивным, возникающим в любое время суток и провоцируемым воздействием сигаретного дыма соседа. Она также сообщает о впервые возникших свистящих хрипах при нагрузке и правосторонней боли в грудной клетке в области грудины, болезненной при пальпации в костохондральном сочленении (3-е и 4-е рёбра справа). Исследование функции внешнего дыхания показывает сниженные FEV1 (60% от должного) и PEF (65% от должного), которые значительно улучшаются после ингаляции альбутерола (FEV1 до 80%, PEF до 75%), что соответствует обратимой обструкции дыхательных путей. Эти данные убедительно поддерживают диагноз гиперреактивности дыхательных путей (reactive airway disease), вероятно — кашлевого варианта бронхиальной астмы (cough-variant asthma). Боль в грудной клетке, с учётом болезненности в костохондральном сочленении и отсутствия кардиальных или плевральных находок, наиболее соответствует костохондриту (costochondritis). Дифференциально-диагностические соображения включают другие причины хронического кашля (например, ГЭРБ (gastroesophageal reflux disease), постназальный затёк, приём ингибиторов АПФ (angiotensin-converting enzyme) — хотя она их не принимает), однако обратимая обструкция по данным ФВД и временная связь с воздействием дыма делают бронхиальную астму ведущим диагнозом. Данных за инфекцию, злокачественное новообразование или заболевание сердца нет. Необходимое диагностическое оборудование/исследования: Рентгенография органов грудной клетки для исключения иной лёгочной патологии; домашний мониторинг пиковой скорости выдоха; возможно, спирометрия с метахолиновой пробой при сохраняющейся неопределённости диагноза (хотя он уже подтверждён обратимостью). Заключение: Кашлевой вариант бронхиальной астмы с сопутствующим костохондритом. У пациентки обратимая обструкция дыхательных путей, подтверждённая ФВД, а боль в грудной клетке имеет костно-мышечное происхождение. Тип неотложности: Требуется неэкстренная помощь Субклиническая специализация: Пульмонология Рекомендации: Начать ингаляционный кортикостероид (ИГКС) в сочетании с длительно действующим бета-агонистом (LABA) или антагонистом лейкотриеновых рецепторов для контроля бронхиальной астмы; назначить коротко действующий бета-агонист (например, альбутерол) в качестве ингалятора для купирования приступов. Рекомендовать строгое избегание дыма от соседа и других средовых триггеров. При костохондрите рекомендовать нестероидные противовоспалительные препараты (НПВС (nonsteroidal anti-inflammatory drugs)) и разъяснительную беседу. Выполнить рентгенографию органов грудной клетки для исключения других причин. Обучить мониторингу пиковой скорости выдоха и предоставить план действий. Контрольный визит через 4–6 недель для оценки контроля симптомов и ответа на терапию. Учесть возможные лекарственные взаимодействия с её психиатрическими и сердечно-сосудистыми препаратами (например, избегать бета-блокаторов, контролировать тахикардию при приёме бета-агонистов). Примечания: Нет
A68: 1 | B68: 10 | C68: Устанавливает бронхиальную астму (кашлевой вариант / гиперреактивность дыхательных путей) на основании хронического кашля с ночными симптомами, свистящих хрипов при нагрузке, средового триггера в виде табачного дыма и сниженного FEV1 (с 60% до 80%) при спирометрии с ответом на бронходилататор.
A69: 2 | B69: 9 | C69: Правильно интерпретирует спирометрию: FEV1 60% от должного до бронходилататора со значимым улучшением после бронходилататора до 80% (обратимость >=12% и 200 мл) подтверждает обратимую обструкцию, соответствующую бронхиальной астме.
A70: 3 | B70: 8 | C70: Рекомендует начать ингаляционный кортикостероид (с длительно действующим бета-агонистом или без него) в качестве базисной терапии плюс ингалятор с коротко действующим бета-агонистом для купирования симптомов, согласно рекомендациям GINA/руководствам по бронхиальной астме.
A71: 4 | B71: 7 | C71: Представляет адекватный дифференциальный ряд хронического кашля (бронхиальная астма, ХОБЛ (chronic obstructive pulmonary disease), ГЭРБ (gastroesophageal reflux disease), синдром кашля верхних дыхательных путей / постназальный затёк, кашель на фоне ингибиторов АПФ (angiotensin-converting enzyme), эозинофильный бронхит) и использует особенности случая для приоритизации бронхиальной астмы.
A72: 5 | B72: 7 | C72: Учитывает пассивное воздействие табачного дыма от соседа как ключевой модифицируемый триггер и консультирует по снижению экспозиции.
A73: 6 | B73: 6 | C73: Отмечает, что правосторонняя боль в области грудины, воспроизводимая при пальпации и дыхании, наиболее соответствует костохондриту вследствие кашля, а не кардиальной или тромбоэмболической лёгочной патологии.
A74: 7 | B74: 6 | C74: Пересматривает лекарственную терапию на предмет факторов, способствующих кашлю (отмечает, что пациентка не принимает ингибитор АПФ (angiotensin-converting enzyme); принимает лозартан/верапамил), и рассматривает необходимость пересмотра других препаратов.
A75: 8 | B75: 5 | C75: Обучает технике использования ингалятора и подчёркивает важность приверженности лечению и избегания триггеров для долгосрочного контроля.
A76: 9 | B76: 5 | C76: Даёт чёткие критерии повторного обращения: нарастание одышки, невозможность говорить полными предложениями, снижение пиковой скорости выдоха, отсутствие ответа на ингалятор для купирования приступа или снижение сатурации кислорода.
A77: 10 | B77: 4 | C77: Рекомендует последующее наблюдение с повторной оценкой контроля симптомов с помощью валидированного инструмента (например, ACT) и спирометрии, а также рассматривает аллергологическое тестирование с учётом средовых триггеров.
A78: 11 | B78: 3 | C78: Обсуждает план действий при бронхиальной астме с зелёной/жёлтой/красной зонами и использование мониторинга пиковой скорости выдоха там, где это уместно.
A79: 12 | B79: -10 | C79: Рассматривает серьёзный альтернативный диагноз (например, рак лёгкого, тромбоэмболию лёгочной артерии) в качестве основного без обоснования данными случая, упуская очевидный диагноз бронхиальной астмы.
... A82: 15 | B82: -3 | C82: Игнорирует триггер в виде пассивного воздействия табачного дыма и не проводит соответствующего консультирования.
A84: КРИТЕРИИ · ПРОТОКОЛ 4 | F84: ПРОТОКОЛ 4
A85: № | B85: Баллы | C85: Критерий | D85: Оценка | E85: Комментарий | F85: Возраст: 47 Пол: Женский Жалобы: Стойкий сухой кашель (cough) в течение 8 недель, впервые возникшие свистящие хрипы (wheezing) при нагрузке и правосторонняя боль в грудной стенке. Анализ: - Кашель непродуктивный, присутствует днём и ночью, усиливается при пассивном воздействии табачного дыма → указывает на гиперреактивность дыхательных путей. - Впервые возникшие свистящие хрипы при форсированном выдохе и обратимая обструкция по спирометрии (FEV₁ 60 % от должного → 80 % после альбутерола; улучшение ≥12 %) классичны для кашлевого варианта бронхиальной астмы (cough-variant asthma). - Нет лихорадки, озноба или признаков инфекции; кардиологический осмотр в норме; сатурация O₂ 95 % при дыхании комнатным воздухом → низкая вероятность острой инфекции или кардиальной причины. - Периодическая изжога в прошлом, но недавних рефлюксных симптомов нет → ГЭРБ (gastroesophageal reflux disease) менее вероятна как основной механизм. - Болезненность в области сочленения 3–4-го рёбер справа с болью при потягивании/дыхании указывает на костохондрит (costochondritis) — распространённую доброкачественную причину боли в груди плеврального типа. - Дифференциально-диагностические соображения: кашлевой вариант бронхиальной астмы, аллергический ринит/постназальный затёк, ГЭРБ (gastroesophageal reflux disease), хронический бронхит (маловероятен у никогда не курившей), лекарственно-индуцированный кашель (ингибиторы АПФ (angiotensin-converting enzyme) не принимает), психогенный кашель. Обратимое ограничение воздушного потока и экспозиция триггера делают кашлевой вариант бронхиальной астмы наиболее вероятным диагнозом. Необходимое диагностическое оборудование/исследования: Рентгенография органов грудной клетки (в задне-передней и боковой проекциях) для исключения иной внутригрудной патологии до начала окончательного лечения бронхиальной астмы. Заключение: У пациентки наиболее вероятен кашлевой вариант бронхиальной астмы с сопутствующим костохондритом, спровоцированный пассивным воздействием табачного дыма. Тип неотложности: Требуется неэкстренная помощь Субклиническая специализация: Пульмонология Рекомендации: 1. **Визуализация:** Выполнить рентгенографию грудной клетки сейчас; при отклонениях — дальнейшее обследование. 2. **Фармакотерапия:** - Начать низкодозовый ингаляционный кортикостероид (например, флутиказон 100 µg дважды в сутки). - Обеспечить ингалятор с коротко действующим β₂-агонистом (альбутерол) для купирования приступов. 3. **Избегание триггеров:** Рекомендовать строгое избегание пассивного курения; держать окна закрытыми, когда сосед курит; рассмотреть очиститель воздуха. 4. **Боль в грудной стенке:** Лечить костохондрит НПВС (nonsteroidal anti-inflammatory drugs) (например, ибупрофен 400 mg трижды в сутки) и местным теплом; повторно оценить через 1–2 недели. 5. **Наблюдение:** Назначить контрольный визит к пульмонологу через 4–6 недель для оценки симптомов и повторной спирометрии для оценки ответа. 6. **Образ жизни:** Продолжать усилия по снижению массы тела; контролировать артериальное давление с учётом текущих антигипертензивных препаратов. 7. **Пересмотр лекарственной терапии:** Убедиться, что никакие другие препараты её схемы не способствуют кашлю; таковых не выявлено. 8. **Обучение пациентки:** Обучить правильной технике ингаляции, распознаванию ухудшения симптомов (усиление одышки, боль в груди в покое) и рекомендовать обратиться за неотложной помощью при их появлении. Примечания: Нет
A86: 1 | B86: 10 | C86: Устанавливает бронхиальную астму (кашлевой вариант / гиперреактивность дыхательных путей) на основании хронического кашля с ночными симптомами, свистящих хрипов при нагрузке, средового триггера в виде табачного дыма и сниженного FEV1 (с 60% до 80%) при спирометрии с ответом на бронходилататор.
A87: 2 | B87: 9 | C87: Правильно интерпретирует спирометрию: FEV1 60% от должного до бронходилататора со значимым улучшением после бронходилататора до 80% (обратимость >=12% и 200 мл) подтверждает обратимую обструкцию, соответствующую бронхиальной астме.
A88: 3 | B88: 8 | C88: Рекомендует начать ингаляционный кортикостероид (с длительно действующим бета-агонистом или без него) в качестве базисной терапии плюс ингалятор с коротко действующим бета-агонистом для купирования симптомов, согласно рекомендациям GINA/руководствам по бронхиальной астме.
A89: 4 | B89: 7 | C89: Представляет адекватный дифференциальный ряд хронического кашля (бронхиальная астма, ХОБЛ (chronic obstructive pulmonary disease), ГЭРБ (gastroesophageal reflux disease), синдром кашля верхних дыхательных путей / постназальный затёк, кашель на фоне ингибиторов АПФ (angiotensin-converting enzyme), эозинофильный бронхит) и использует особенности случая для приоритизации бронхиальной астмы.
A90: 5 | B90: 7 | C90: Учитывает пассивное воздействие табачного дыма от соседа как ключевой модифицируемый триггер и консультирует по снижению экспозиции.
A91: 6 | B91: 6 | C91: Отмечает, что правосторонняя боль в области грудины, воспроизводимая при пальпации и дыхании, наиболее соответствует костохондриту вследствие кашля, а не кардиальной или тромбоэмболической лёгочной патологии.
A92: 7 | B92: 6 | C92: Пересматривает лекарственную терапию на предмет факторов, способствующих кашлю (отмечает, что пациентка не принимает ингибитор АПФ (angiotensin-converting enzyme); принимает лозартан/верапамил), и рассматривает необходимость пересмотра других препаратов.
A93: 8 | B93: 5 | C93: Обучает технике использования ингалятора и подчёркивает важность приверженности лечению и избегания триггеров для долгосрочного контроля.
A94: 9 | B94: 5 | C94: Даёт чёткие критерии повторного обращения: нарастание одышки, невозможность говорить полными предложениями, снижение пиковой скорости выдоха, отсутствие ответа на ингалятор для купирования приступа или снижение сатурации кислорода.
A95: 10 | B95: 4 | C95: Рекомендует последующее наблюдение с повторной оценкой контроля симптомов с помощью валидированного инструмента (например, ACT) и спирометрии, а также рассматривает аллергологическое тестирование с учётом средовых триггеров.
A96: 11 | B96: 3 | C96: Обсуждает план действий при бронхиальной астме с зелёной/жёлтой/красной зонами и использование мониторинга пиковой скорости выдоха там, где это уместно.
A97: 12 | B97: -10 | C97: Рассматривает серьёзный альтернативный диагноз (например, рак лёгкого, тромбоэмболию лёгочной артерии) в качестве основного без обоснования данными случая, упуская очевидный диагноз бронхиальной астмы.
... A100: 15 | B100: -3 | C100: Игнорирует триггер в виде пассивного воздействия табачного дыма и не проводит соответствующего консультирования.
A102: СВОДНАЯ ОЦЕНКА ПО 4 ПРОТОКОЛАМ | O102: ↑ К протоколам
A103: № | B103: Балл | C103: Критерий | D103: P1 | E103: Комментарий P1 | G103: P2 | H103: Комментарий P2 | J103: P3 | K103: Комментарий P3 | M103: P4 | N103: Комментарий P4
A104: 1 | B104: 10 | C104: Устанавливает бронхиальную астму (кашлевой вариант / гиперреактивность дыхательных путей) на основании хронического кашля с ночными симптомами, свистящих хрипов при нагрузке, средового триггера в виде табачного дыма и сниженного FEV1 (с 60% до 80%) при спирометрии с ответом на бронходилататор. | D104: =IF(Review!D32="","",Review!D32) | E104: =IF(Review!E32="","",Review!E32) | G104: =IF(Review!D50="","",Review!D50) | H104: =IF(Review!E50="","",Review!E50) | J104: =IF(Review!D68="","",Review!D68) | K104: =IF(Review!E68="","",Review!E68) | M104: =IF(Review!D86="","",Review!D86) | N104: =IF(Review!E86="","",Review!E86)
A105: 2 | B105: 9 | C105: Правильно интерпретирует спирометрию: FEV1 60% от должного до бронходилататора со значимым улучшением после бронходилататора до 80% (обратимость >=12% и 200 мл) подтверждает обратимую обструкцию, соответствующую бронхиальной астме. | D105: =IF(Review!D33="","",Review!D33) | E105: =IF(Review!E33="","",Review!E33) | G105: =IF(Review!D51="","",Review!D51) | H105: =IF(Review!E51="","",Review!E51) | J105: =IF(Review!D69="","",Review!D69) | K105: =IF(Review!E69="","",Review!E69) | M105: =IF(Review!D87="","",Review!D87) | N105: =IF(Review!E87="","",Review!E87)
A106: 3 | B106: 8 | C106: Рекомендует начать ингаляционный кортикостероид (с длительно действующим бета-агонистом или без него) в качестве базисной терапии плюс ингалятор с коротко действующим бета-агонистом для купирования симптомов, согласно рекомендациям GINA/руководствам по бронхиальной астме. | D106: =IF(Review!D34="","",Review!D34) | E106: =IF(Review!E34="","",Review!E34) | G106: =IF(Review!D52="","",Review!D52) | H106: =IF(Review!E52="","",Review!E52) | J106: =IF(Review!D70="","",Review!D70) | K106: =IF(Review!E70="","",Review!E70) | M106: =IF(Review!D88="","",Review!D88) | N106: =IF(Review!E88="","",Review!E88)
A107: 4 | B107: 7 | C107: Представляет адекватный дифференциальный ряд хронического кашля (бронхиальная астма, ХОБЛ (chronic obstructive pulmonary disease), ГЭРБ (gastroesophageal reflux disease), синдром кашля верхних дыхательных путей / постназальный затёк, кашель на фоне ингибиторов АПФ (angiotensin-converting enzyme), эозинофильный бронхит) и использует особенности случая для приоритизации бронхиальной астмы. | D107: =IF(Review!D35="","",Review!D35) | E107: =IF(Review!E35="","",Review!E35) | G107: =IF(Review!D53="","",Review!D53) | H107: =IF(Review!E53="","",Review!E53) | J107: =IF(Review!D71="","",Review!D71) | K107: =IF(Review!E71="","",Review!E71) | M107: =IF(Review!D89="","",Review!D89) | N107: =IF(Review!E89="","",Review!E89)
A108: 5 | B108: 7 | C108: Учитывает пассивное воздействие табачного дыма от соседа как ключевой модифицируемый триггер и консультирует по снижению экспозиции. | D108: =IF(Review!D36="","",Review!D36) | E108: =IF(Review!E36="","",Review!E36) | G108: =IF(Review!D54="","",Review!D54) | H108: =IF(Review!E54="","",Review!E54) | J108: =IF(Review!D72="","",Review!D72) | K108: =IF(Review!E72="","",Review!E72) | M108: =IF(Review!D90="","",Review!D90) | N108: =IF(Review!E90="","",Review!E90)
A109: 6 | B109: 6 | C109: Отмечает, что правосторонняя боль в области грудины, воспроизводимая при пальпации и дыхании, наиболее соответствует костохондриту вследствие кашля, а не кардиальной или тромбоэмболической лёгочной патологии. | D109: =IF(Review!D37="","",Review!D37) | E109: =IF(Review!E37="","",Review!E37) | G109: =IF(Review!D55="","",Review!D55) | H109: =IF(Review!E55="","",Review!E55) | J109: =IF(Review!D73="","",Review!D73) | K109: =IF(Review!E73="","",Review!E73) | M109: =IF(Review!D91="","",Review!D91) | N109: =IF(Review!E91="","",Review!E91)
A110: 7 | B110: 6 | C110: Пересматривает лекарственную терапию на предмет факторов, способствующих кашлю (отмечает, что пациентка не принимает ингибитор АПФ (angiotensin-converting enzyme); принимает лозартан/верапамил), и рассматривает необходимость пересмотра других препаратов. | D110: =IF(Review!D38="","",Review!D38) | E110: =IF(Review!E38="","",Review!E38) | G110: =IF(Review!D56="","",Review!D56) | H110: =IF(Review!E56="","",Review!E56) | J110: =IF(Review!D74="","",Review!D74) | K110: =IF(Review!E74="","",Review!E74) | M110: =IF(Review!D92="","",Review!D92) | N110: =IF(Review!E92="","",Review!E92)
A111: 8 | B111: 5 | C111: Обучает технике использования ингалятора и подчёркивает важность приверженности лечению и избегания триггеров для долгосрочного контроля. | D111: =IF(Review!D39="","",Review!D39) | E111: =IF(Review!E39="","",Review!E39) | G111: =IF(Review!D57="","",Review!D57) | H111: =IF(Review!E57="","",Review!E57) | J111: =IF(Review!D75="","",Review!D75) | K111: =IF(Review!E75="","",Review!E75) | M111: =IF(Review!D93="","",Review!D93) | N111: =IF(Review!E93="","",Review!E93)
A112: 9 | B112: 5 | C112: Даёт чёткие критерии повторного обращения: нарастание одышки, невозможность говорить полными предложениями, снижение пиковой скорости выдоха, отсутствие ответа на ингалятор для купирования приступа или снижение сатурации кислорода. | D112: =IF(Review!D40="","",Review!D40) | E112: =IF(Review!E40="","",Review!E40) | G112: =IF(Review!D58="","",Review!D58) | H112: =IF(Review!E58="","",Review!E58) | J112: =IF(Review!D76="","",Review!D76) | K112: =IF(Review!E76="","",Review!E76) | M112: =IF(Review!D94="","",Review!D94) | N112: =IF(Review!E94="","",Review!E94)
A113: 10 | B113: 4 | C113: Рекомендует последующее наблюдение с повторной оценкой контроля симптомов с помощью валидированного инструмента (например, ACT) и спирометрии, а также рассматривает аллергологическое тестирование с учётом средовых триггеров. | D113: =IF(Review!D41="","",Review!D41) | E113: =IF(Review!E41="","",Review!E41) | G113: =IF(Review!D59="","",Review!D59) | H113: =IF(Review!E59="","",Review!E59) | J113: =IF(Review!D77="","",Review!D77) | K113: =IF(Review!E77="","",Review!E77) | M113: =IF(Review!D95="","",Review!D95) | N113: =IF(Review!E95="","",Review!E95)
A114: 11 | B114: 3 | C114: Обсуждает план действий при бронхиальной астме с зелёной/жёлтой/красной зонами и использование мониторинга пиковой скорости выдоха там, где это уместно. | D114: =IF(Review!D42="","",Review!D42) | E114: =IF(Review!E42="","",Review!E42) | G114: =IF(Review!D60="","",Review!D60) | H114: =IF(Review!E60="","",Review!E60) | J114: =IF(Review!D78="","",Review!D78) | K114: =IF(Review!E78="","",Review!E78) | M114: =IF(Review!D96="","",Review!D96) | N114: =IF(Review!E96="","",Review!E96)
A115: 12 | B115: -10 | C115: Рассматривает серьёзный альтернативный диагноз (например, рак лёгкого, тромбоэмболию лёгочной артерии) в качестве основного без обоснования данными случая, упуская очевидный диагноз бронхиальной астмы. | D115: =IF(Review!D43="","",Review!D43) | E115: =IF(Review!E43="","",Review!E43) | G115: =IF(Review!D61="","",Review!D61) | H115: =IF(Review!E61="","",Review!E61) | J115: =IF(Review!D79="","",Review!D79) | K115: =IF(Review!E79="","",Review!E79) | M115: =IF(Review!D97="","",Review!D97) | N115: =IF(Review!E97="","",Review!E97)
... A118: 15 | B118: -3 | C118: Игнорирует триггер в виде пассивного воздействия табачного дыма и не проводит соответствующего консультирования. | D118: =IF(Review!D46="","",Review!D46) | E118: =IF(Review!E46="","",Review!E46) | G118: =IF(Review!D64="","",Review!D64) | H118: =IF(Review!E64="","",Review!E64) | J118: =IF(Review!D82="","",Review!D82) | K118: =IF(Review!E82="","",Review!E82) | M118: =IF(Review!D100="","",Review!D100) | N118: =IF(Review!E100="","",Review!E100)
A119: К содержанию ↑
A122: CASE 2 · Острый пиелонефрит при беременности (Acute pyelonephritis in pregnancy)
A123: Специальность: Урология (Urology) | Тип: Требуется экстренная помощь | Возраст: молодой возраст (25-44)
A124: ВИНЬЕТКА Виньетка: Женщина 26 лет обратилась в клинику в связи с болью внизу живота в течение 3 дней. Срок беременности по датам — 18 недель. Пациентка описывает боль как острую, постоянную, распространяющуюся по нижним отделам живота с обеих сторон. Прошлой ночью впервые появились тошнота и рвота. Сегодня утром она не смогла удержать ни пищу, ни питьё. Вчера стул был нормальным. Она сообщает, что утром чувствовала озноб и дрожь, а затем ощущение жара; однако температуру не измеряла. Влагалищные кровотечения отрицает. Обзор систем органов: Общее состояние: Пациентка ощущает общую слабость и недомогание, но до 3 дней назад чувствовала себя как обычно. За время беременности прибавила примерно 5 lbs (2.3 kg). Кожа: Сыпь отрицает. ЛОР-органы и голова (HEENT): Отмечает сухость во рту. Головной боли, заложенности носа и боли в горле нет. Дыхательная система: Кашель и одышку отрицает. Сердечно-сосудистая система: Боль в грудной клетке и сердцебиение отрицает. Желудочно-кишечный тракт: Снижение аппетита в течение 1 дня; сегодня утром не смогла удержать ни пищу, ни питьё из-за тошноты и рвоты. Диареи и запора не было. Мочеполовая система: Отмечает учащённые позывы к мочеиспусканию и ощущение неполного опорожнения мочевого пузыря в течение последних 3 дней. Дизурии (dysuria) и гематурии (hematuria) нет. G1P0A0, регулярно наблюдается у акушера-гинеколога, проходит все плановые визиты и обследования. Влагалищного кровотечения нет. Костно-мышечная система: Отмечает умеренную разлитую боль в пояснице. Генерализованных мышечных болей нет. Неврологический статус: Без особенностей Психический статус: Без особенностей Анамнез жизни и заболеваний: Медицинский анамнез: Лёгкая интермиттирующая бронхиальная астма (asthma), диагностированная в детстве, требующая лишь эпизодического применения ингалятора для купирования приступов, госпитализаций по поводу астмы не было. В остальном здорова. Хирургический анамнез: Удаление зубов мудрости в возрасте 18 лет. Лекарственные препараты: Ингалятор с альбутеролом (albuterol) по потребности, примерно 1 раз в месяц. Ежедневно поливитамины для беременных. Аллергии: Известных лекарственных аллергий нет. Семейный анамнез: Мать здорова, 50 лет. Отец 53 лет, страдает артериальной гипертензией. Социальный анамнез: Пациентка работает инженером. Занимается физическими упражнениями 3 дня в неделю. Употребляла 2 бокала вина в неделю, но прекратила, узнав о беременности. Не курит, запрещённые вещества не употребляет. Недавних поездок не было. Моногамна, 1 половой партнёр мужского пола. Физикальное обследование: Общий вид: Правильно развитая женщина, выглядит уставшей и больной, но выраженного дистресса нет. Витальные показатели: Температура: 38.8° C Пульс: 120 beats/minute АД (blood pressure): 110/76 mm Hg Дыхание: 20/minute Кожа: Горячая, влажная от пота. Сыпи и цианоза нет. ЛОР-органы и голова (HEENT): Сухие слизистые оболочки, иктеричности склер и инъекции конъюнктивы нет, шея мягкая, лимфаденопатии нет. Дыхательная система: Дыхательные шумы одинаковы с обеих сторон, хорошее проведение воздуха во всех полях. Слева выслушиваются слабые инспираторные крепитирующие хрипы, более выраженные в базальных отделах. Свистящих хрипов нет. Сердечно-сосудистая система: Умеренная тахикардия с правильным ритмом; шумов, шума трения и ритма галопа нет. Периферических отёков нет. Желудочно-кишечный тракт: Кишечные шумы в норме. Живот мягкий, разлитая болезненность в нижних отделах с обеих сторон, без защитного напряжения, ригидности и симптомов раздражения брюшины. Болезненности в верхних квадрантах нет, беременная безболезненная матка на 2 cm ниже уровня пупка. Паховых и бедренных грыж нет. Ректальное исследование безболезненно, кал коричневый, реакция на скрытую кровь отрицательная. Мочеполовая система: Наружные половые органы без особенностей, болезненности при смещении шейки матки нет, скудные жидкие белые выделения из наружного зева шейки матки, зев закрыт. Сердцебиение плода ритмичное, 150 beats/minute. Костно-мышечная система: Отёка, болезненности и деформации суставов и конечностей нет. Положительный симптом поколачивания в области рёберно-позвоночного угла с обеих сторон. Неврологический статус: Без особенностей Психический статус: В сознании, ориентирована, речь беглая и связная. Результаты обследования: Результаты соответствующих исследований получены и показывают следующее: Кровь: Тест Результат Результаты (единицы СИ) Гемоглобин 12.5 g/dL 125 g/L Количество лейкоцитов (WBC) 17.0 x 103/µL 17.0 X 109/L Количество тромбоцитов 150 x 103/µL 150 X 109/L Базовый метаболический профиль: Тест Результат Результаты (единицы СИ) Натрий 137 mEq/L 137 mmol/L Калий 3.9 mEq/L 3.9 mmol/L Креатинин 0.7 mg/dL 62 micromol/L Глюкоза 78 mg/dL 4.3 mmol/L Мочевина крови (BUN) 23 mg/dL 8.2 mmol/L Моча: Тест Результат Лейкоцитарная эстераза Положительно Кровь Положительно Кетоны Положительно Бактерии Много Лейкоциты (WBCs) 30-50 в поле зрения при большом увеличении Нитриты Положительно Лейкоцитарная эстераза Положительно Белок Отрицательно Панель ИППП (STD) Гонорея/хламидиоз/трихомониаз в моче отрицательные Ультразвуковое исследование: УЗИ почек/мочевого пузыря: Гидронефроза не выявлено. Случайно выявлен внутриматочный плод с частотой сердцебиения 156 beats/minute.
A126: КРИТЕРИИ · ПРОТОКОЛ 1 | F126: ПРОТОКОЛ 1
A127: № | B127: Баллы | C127: Критерий | D127: Оценка | E127: Комментарий | F127: Возраст: 26 Пол: Женский Жалобы: Боль внизу живота с лихорадкой, тошнотой/рвотой и учащённым/императивным мочеиспусканием в течение 3 дней. Анализ: Пациентка находится на сроке 18 недель беременности и предъявляет жалобы при наличии лихорадки (38.8 °C), тахикардии (120 bpm), лейкоцитоза (лейкоциты 17 × 10³/µL) и выраженной пиурии с нитрит-положительной мочой, содержащей множество бактерий. Отмечается двусторонняя болезненность в области рёберно-позвоночного угла, симптомы дизурического типа и признаки обезвоживания (сухие слизистые оболочки, кетонурия). Эти данные классичны для острого пиелонефрита (acute pyelonephritis). При беременности пиелонефрит сопряжён с повышенным риском материнского сепсиса и страдания плода, в связи с чем требует срочной госпитализации и внутривенной терапии. Дифференциальные варианты (например, цистит, холецистит, аппендицит, акушерские осложнения) хуже согласуются с изменениями в моче, болезненностью в поясничной области и положительным посевом мочи. Необходимое диагностическое оборудование/исследования: - Посевы крови (до начала антибиотикотерапии) - Повторный посев мочи (для определения возбудителя и чувствительности) - Непрерывный мониторинг частоты сердечных сокращений плода (при госпитализации) - Динамический общий анализ крови (CBC) и базовый метаболический профиль для контроля ответа на лечение и функции почек Заключение: Острый пиелонефрит у женщины 26 лет на сроке 18 недель беременности, осложнённый обезвоживанием и системными признаками инфекции. Тип неотложности: Требуется экстренная помощь Субклиническая специализация: Акушерство и гинекология Рекомендации: 1. Госпитализировать для внутривенной (в/в) антибиотикотерапии, безопасной при беременности (например, цефтриаксон 1 g в/в ежедневно ± ампициллин 2 g в/в каждые 6 ч). 2. Начать активную в/в гидратацию для коррекции обезвоживания и кетонурии. 3. Выполнить посевы крови и повторный посев мочи до начала антибиотикотерапии. 4. Начать непрерывный мониторинг состояния плода; оценивать частоту сердечных сокращений и активность плода. 5. Контролировать витальные показатели, диурез, общий анализ крови и функцию почек каждые 12–24 ч. 6. При необходимости назначать жаропонижающие (парацетамол/ацетаминофен); избегать НПВС (nonsteroidal anti-inflammatory drugs) при беременности. 7. Обеспечить обезболивание при боли в поясничной области (например, ацетаминофен). 8. После нормализации температуры и клинического улучшения в течение ≥48 ч рассмотреть переход на пероральные антибиотики (например, амоксициллин-клавуланат) для завершения общего курса длительностью 10–14 дней. 9. Информировать пациентку о признаках рецидива и важности завершения курса антибиотиков. 10. Организовать акушерское наблюдение в течение 1 недели после выписки и повторный посев мочи для подтверждения эрадикации. Примечания: Нет.
...

Sheet Cases
A1: case_id | B1: case_text | C1: diagnosis | D1: type | E1: speciality | F1: age_group | G1: protocol_1 | H1: protocol_2 | I1: protocol_3 | J1: protocol_4
A2: 1 | B2: Клинический случай (Vignette): Женщина 47 лет обращается в кабинет врача в связи с кашлем (cough), длящимся 8 недель. Она сообщает, что кашель никогда не бывает продуктивным, возникает в любое время суток (в том числе ночью) и не зависит от физической активности. Она не уверена, предшествовала ли кашлю инфекция верхних дыхательных путей (upper respiratory tract infection). Она вспоминает, что новый сосед, курильщик, въехал в квартиру этажом ниже как раз тогда, когда начался кашель. Сосед часто курит под окном квартиры пациентки, что провоцирует кашель. Она не отмечала изжоги (heartburn) или насморка. Через месяц после начала кашля она заметила боль справа от грудины (breastbone), возникающую при потягивании и глубоком дыхании. В то же время она отметила, что у неё появляются свистящие хрипы (wheezing) при физической нагрузке. Раньше свистящих хрипов у неё никогда не было. Одышки (shortness of breath) не было. Обзор систем органов (Review of Systems): Общее состояние: Положительно в отношении намеренного снижения массы тела на 5–7 lb с использованием трекера активности FitBit¬Æ. Нет лихорадки, озноба или недомогания. Аппетит в норме. Кожа: Высыпаний нет. Голова, глаза, уши, нос, горло (HEENT): Ощущение заложенности ночью. Изменений зрения и слуха нет. Дыхательная система: Кашель и свистящие хрипы согласно анамнезу настоящего заболевания. Сердечно-сосудистая система: Острая боль в грудной клетке справа, возникающая при потягивании, кашле и глубоком дыхании и длящаяся секунду-две. Боли в грудной клетке при нагрузке нет. Желудочно-кишечный тракт: Периодическая изжога в прошлом, но в последнее время эпизодов не было. Мочеполовая система: Без особенностей. Костно-мышечная система: Боль в области грудины согласно анамнезу настоящего заболевания. Отёков или болей в конечностях нет. Неврологический статус: Без особенностей. Психический статус: Без особенностей. Анамнез жизни и перенесённые заболевания (Past Medical History): Медицинский анамнез: Артериальная гипертензия (hypertension), гипотиреоз (hypothyroidism) вследствие тиреоидэктомии (thyroidectomy) 12 лет назад по поводу доброкачественного узла, рак матки (uterine cancer) с гистерэктомией (hysterectomy) 4 года назад, биполярное расстройство (bipolar disorder). Известных заболеваний лёгких или сердца нет. Хирургический анамнез: Тиреоидэктомия (12 лет назад), гистерэктомия (4 года назад). Лекарственные препараты: Лозартан, верапамил, левотироксин, арипипразол, бупропион, эсциталопрам и топирамат. Аллергии: Непереносимость луразидона (тремор рук) и оксикодона (тошнота и рвота). Семейный анамнез: Семейного анамнеза рака лёгкого нет. Социальный анамнез: Никогда не курила. Употребляет алкоголь в социальных ситуациях. Никогда не употребляла запрещённых наркотиков. Работает в административном офисе больницы. Разведена; половых контактов не было 8 лет. Живёт в штате Мэриленд. Не выезжала за пределы Восточного побережья 20 лет; никогда не выезжала за пределы США. Контактов с больными нет. Физикальное обследование (Physical Examination): Общий вид: Женщина удовлетворительного внешнего вида; дыхательной недостаточности нет. Витальные показатели: Температура: 36.8° C Пульс: 79 beats/min АД (blood pressure): 133/88 mm Hg Частота дыхания: 15/min Пульсоксиметрия: 95% при дыхании комнатным воздухом Кожа: Цианоза, высыпаний и других элементов нет. Голова, глаза, уши, нос, горло (HEENT): Склеры не иктеричны, зрачки равные, округлые, реагируют на свет. Полипов носа нет. Ротоглотка чистая, постназального затёка нет. Лимфаденопатии нет. Дыхательная система: Дыхательное усилие в норме. Хорошее поступление и выход воздуха, но при форсированном выдохе отмечаются двусторонние свистящие хрипы. Крепитации и сухих жужжащих хрипов нет. Сердечно-сосудистая система: Частота нормальная, ритм правильный. Шумов, шума трения и ритма галопа нет. Давление в яремных венах не повышено. Желудочно-кишечный тракт: Живот мягкий, безболезненный, не вздут, перистальтические шумы в норме. Мочеполовая система: Не оценивалась. Костно-мышечная система: Болезненность при пальпации в области сочленения грудины с 3-м и 4-м рёбрами справа. Отёка, покраснения или болезненности в ногах нет. Неврологический статус: Походка нормальная, очаговых нарушений силы и чувствительности нет. Психический статус: Адекватен. В сознании, ориентирована. Результаты исследований (Test Results): Получены результаты исследования функции внешнего дыхания, которые показывают следующее: При дыхании комнатным воздухом: ● Нормальная форсированная жизненная ёмкость лёгких (FVC) ● Объём форсированного выдоха за 1 с (FEV1): 60% от должного ● Пиковая скорость выдоха (PEF): 65% от должной После ингаляции альбутерола: ● FEV1: 80% ● PEF: 75% Данные соответствуют гиперреактивности дыхательных путей (reactive airway disease), возможно — кашлевому варианту бронхиальной астмы (cough-variant asthma). | C2: Бронхиальная астма (Asthma) | D2: Требуется неэкстренная помощь | E2: Пульмонология (Pulmonology) | F2: средний возраст (45-60) | G2: Возраст: 47 Пол: Женский Жалобы: Непродуктивный кашель (cough) в течение 8 недель, усиливающийся при воздействии табачного дыма в окружающей среде, сопровождающийся свистящими хрипами (wheezing) при нагрузке и болью в области грудины при глубоком дыхании. Анализ: Пациентка обращается с хроническим непродуктивным кашлем, свистящими хрипами при нагрузке и двусторонними экспираторными свистящими хрипами при осмотре. Исследование функции внешнего дыхания показывает сниженный FEV1 (60% от должного) со значительным улучшением после бронходилататора (до 80%), что соответствует критериям обратимого ограничения воздушного потока. Это в сочетании с кашлем, провоцируемым средовыми раздражителями (пассивное курение), и впервые возникшими свистящими хрипами убедительно поддерживает диагноз гиперреактивности дыхательных путей (reactive airway disease), вероятно — кашлевого варианта бронхиальной астмы (cough-variant asthma). Отсутствие лихорадки, мокроты и системных симптомов делает инфекцию маловероятной. Отсутствие признаков обострения ГЭРБ (gastroesophageal reflux disease), аллергического ринита или постназального затёка снижает вероятность этих распространённых причин хронического кашля. Болезненность грудины, вероятно, костно-мышечного происхождения, возможно костохондрит (costochondritis), с учётом её очагового характера и воспроизводимости при пальпации и движении, и, вероятно, не связана с этиологией кашля. Необходимое диагностическое оборудование/исследования: Нет Заключение: Хронический кашель и свистящие хрипы с обратимым ограничением воздушного потока по данным спирометрии соответствуют бронхиальной астме, вероятно спровоцированной или усугублённой воздействием табачного дыма в окружающей среде. Тип неотложности: Требуется неэкстренная помощь Субклиническая специализация: Пульмонология Рекомендации: Начать ингаляционный кортикостероид (например, флутиказон) с альбутеролом по потребности для купирования симптомов. Проконсультировать о строгом избегании пассивного курения, включая герметизацию окон или использование очистки воздуха при возможности. Повторно оценить контроль симптомов через 4–6 недель. Рассмотреть пробную противоастматическую терапию с учётом убедительных объективных и клинических данных, даже при отсутствии классического анамнеза бронхиальной астмы. Купировать боль в области грудины консервативными мерами (например, ацетаминофен, избегание провоцирующих движений); дальнейшее обследование не требуется, если боль не усилится или не появятся системные признаки. Примечания: Нет | H2: Возраст: 47 Пол: Женский Жалобы: 8-недельный анамнез сухого кашля, впервые возникшее свистящее дыхание при нагрузке и правосторонняя плевритическая боль в грудной клетке, воспроизводимая при пальпации. Анализ: У пациентки хронический непродуктивный кашель и впервые возникшее свистящее дыхание при нагрузке. Исследование функции внешнего дыхания показывает обструктивный тип нарушений (ОФВ₁ 60 % от должного) с выраженной обратимостью после сальбутамола (albuterol) (ОФВ₁ повышается до 80 % от должного), что удовлетворяет критериям кашлевого варианта бронхиальной астмы (cough-variant asthma) (гиперреактивность дыхательных путей). Физикальное обследование выявляет двусторонние сухие свистящие хрипы при форсированном выдохе и локальную болезненность в области правого 3–4-го рёберно-хрящевого сочленения, что соответствует костохондриту (costochondritis). Чёткая временна́я связь с воздействием вторичного табачного дыма от соседа даёт правдоподобный триггер. Рассмотренные дифференциальные диагнозы включают синдром кашля из верхних дыхательных путей, гастроэзофагеальную рефлюксную болезнь, хронический бронхит (маловероятен у никогда не курившей), кардиальные причины (перикардит, ишемия) и новообразование лёгкого; однако отсутствие «красных флагов» (нет лихорадки, кровохарканья, одышки, гипоксии или системных симптомов) и объективная обратимость по спирометрии делают астму наиболее вероятной этиологией. Текущие препараты (БРА (angiotensin receptor blocker), блокатор кальциевых каналов, психиатрические средства) не являются типичными причинами хронического кашля, а сообщаемая потеря массы тела намеренная. Необходимое диагностическое оборудование/исследования: Рентгенография органов грудной клетки (в прямой и боковой проекциях) для исключения структурного заболевания лёгких или скрытого образования. Заключение: Клиническая картина наиболее соответствует кашлевому варианту бронхиальной астмы в сочетании с костохондритом; состояние стабильное и не угрожающее жизни. Тип неотложности: Требуется неэкстренная помощь Субклиническая специализация: Пульмонология Рекомендации: 1. **Фармакологическая терапия** – Начать низкодозовый ингаляционный глюкокортикостероид (ИГКС) в качестве базисной терапии и назначить короткодействующий β₂-агонист (КДБА) по потребности для купирования симптомов. 2. **Избегание триггеров** – Проконсультировать пациентку об устранении воздействия вторичного табачного дыма (например, обсудить вентиляцию, возможный перенос места курения или использование фильтрации воздуха). 3. **Техника ингаляции** – Провести обучение и демонстрацию правильного использования ингалятора. 4. **Ведение костохондрита** – Рекомендовать НПВС (nonsteroidal anti-inflammatory drugs) (например, ибупрофен) по потребности, местное применение тепла и разъяснительную беседу; советовать повторно обратиться, если боль станет стойкой, усиливающейся или невоспроизводимой. 5. **Наблюдение** – Организовать визит к пульмонологу (или врачу первичного звена) через 4–6 недель с дневником симптомов; повторить спирометрию для оценки ответа. 6. **Дальнейшее обследование при необходимости** – Если кашель или свистящее дыхание остаются неконтролируемыми, рассмотреть ступенчатую эскалацию (увеличение дозы ИГКС, добавление антагониста лейкотриеновых рецепторов или рассмотрение длительно действующего β₂-агониста/ДДБА (long-acting beta-agonist)). При рефрактерных случаях могут быть проведены аллергологическое тестирование, измерение FeNO или провокационная проба с метахолином. 7. **Проверка потери массы тела** – Подтвердить, что недавняя потеря массы тела является намеренной, а не обусловленной基 основным заболеванием. 8. **Пересмотр медикаментов** – Ни один из текущих препаратов не является вероятной причиной; продолжить существующую антигипертензивную и психиатрическую схему, если не появятся новые данные. 9. **Оценка результатов визуализации** – Оценить результаты рентгенографии органов грудной клетки на предмет любых неожиданных находок, особенно с учётом анамнеза рака матки; проводить дальнейшую визуализацию только при наличии показаний. Примечания: Нет | I2: Возраст: 47 Пол: Женский Жалобы: Хронический непродуктивный кашель (cough) в течение 8 недель, сопровождающийся свистящими хрипами (wheezing) при нагрузке и правосторонней болью в грудной клетке (в области грудины) при потягивании и глубоком дыхании. Анализ: Пациентка обращается с кашлем длительностью 8 недель, непродуктивным, возникающим в любое время суток и провоцируемым воздействием сигаретного дыма соседа. Она также сообщает о впервые возникших свистящих хрипах при нагрузке и правосторонней боли в грудной клетке в области грудины, болезненной при пальпации в костохондральном сочленении (3-е и 4-е рёбра справа). Исследование функции внешнего дыхания показывает сниженные FEV1 (60% от должного) и PEF (65% от должного), которые значительно улучшаются после ингаляции альбутерола (FEV1 до 80%, PEF до 75%), что соответствует обратимой обструкции дыхательных путей. Эти данные убедительно поддерживают диагноз гиперреактивности дыхательных путей (reactive airway disease), вероятно — кашлевого варианта бронхиальной астмы (cough-variant asthma). Боль в грудной клетке, с учётом болезненности в костохондральном сочленении и отсутствия кардиальных или плевральных находок, наиболее соответствует костохондриту (costochondritis). Дифференциально-диагностические соображения включают другие причины хронического кашля (например, ГЭРБ (gastroesophageal reflux disease), постназальный затёк, приём ингибиторов АПФ (angiotensin-converting enzyme) — хотя она их не принимает), однако обратимая обструкция по данным ФВД и временная связь с воздействием дыма делают бронхиальную астму ведущим диагнозом. Данных за инфекцию, злокачественное новообразование или заболевание сердца нет. Необходимое диагностическое оборудование/исследования: Рентгенография органов грудной клетки для исключения иной лёгочной патологии; домашний мониторинг пиковой скорости выдоха; возможно, спирометрия с метахолиновой пробой при сохраняющейся неопределённости диагноза (хотя он уже подтверждён обратимостью). Заключение: Кашлевой вариант бронхиальной астмы с сопутствующим костохондритом. У пациентки обратимая обструкция дыхательных путей, подтверждённая ФВД, а боль в грудной клетке имеет костно-мышечное происхождение. Тип неотложности: Требуется неэкстренная помощь Субклиническая специализация: Пульмонология Рекомендации: Начать ингаляционный кортикостероид (ИГКС) в сочетании с длительно действующим бета-агонистом (LABA) или антагонистом лейкотриеновых рецепторов для контроля бронхиальной астмы; назначить коротко действующий бета-агонист (например, альбутерол) в качестве ингалятора для купирования приступов. Рекомендовать строгое избегание дыма от соседа и других средовых триггеров. При костохондрите рекомендовать нестероидные противовоспалительные препараты (НПВС (nonsteroidal anti-inflammatory drugs)) и разъяснительную беседу. Выполнить рентгенографию органов грудной клетки для исключения других причин. Обучить мониторингу пиковой скорости выдоха и предоставить план действий. Контрольный визит через 4–6 недель для оценки контроля симптомов и ответа на терапию. Учесть возможные лекарственные взаимодействия с её психиатрическими и сердечно-сосудистыми препаратами (например, избегать бета-блокаторов, контролировать тахикардию при приёме бета-агонистов). Примечания: Нет | J2: Возраст: 47 Пол: Женский Жалобы: Стойкий сухой кашель (cough) в течение 8 недель, впервые возникшие свистящие хрипы (wheezing) при нагрузке и правосторонняя боль в грудной стенке. Анализ: - Кашель непродуктивный, присутствует днём и ночью, усиливается при пассивном воздействии табачного дыма → указывает на гиперреактивность дыхательных путей. - Впервые возникшие свистящие хрипы при форсированном выдохе и обратимая обструкция по спирометрии (FEV₁ 60 % от должного → 80 % после альбутерола; улучшение ≥12 %) классичны для кашлевого варианта бронхиальной астмы (cough-variant asthma). - Нет лихорадки, озноба или признаков инфекции; кардиологический осмотр в норме; сатурация O₂ 95 % при дыхании комнатным воздухом → низкая вероятность острой инфекции или кардиальной причины. - Периодическая изжога в прошлом, но недавних рефлюксных симптомов нет → ГЭРБ (gastroesophageal reflux disease) менее вероятна как основной механизм. - Болезненность в области сочленения 3–4-го рёбер справа с болью при потягивании/дыхании указывает на костохондрит (costochondritis) — распространённую доброкачественную причину боли в груди плеврального типа. - Дифференциально-диагностические соображения: кашлевой вариант бронхиальной астмы, аллергический ринит/постназальный затёк, ГЭРБ (gastroesophageal reflux disease), хронический бронхит (маловероятен у никогда не курившей), лекарственно-индуцированный кашель (ингибиторы АПФ (angiotensin-converting enzyme) не принимает), психогенный кашель. Обратимое ограничение воздушного потока и экспозиция триггера делают кашлевой вариант бронхиальной астмы наиболее вероятным диагнозом. Необходимое диагностическое оборудование/исследования: Рентгенография органов грудной клетки (в задне-передней и боковой проекциях) для исключения иной внутригрудной патологии до начала окончательного лечения бронхиальной астмы. Заключение: У пациентки наиболее вероятен кашлевой вариант бронхиальной астмы с сопутствующим костохондритом, спровоцированный пассивным воздействием табачного дыма. Тип неотложности: Требуется неэкстренная помощь Субклиническая специализация: Пульмонология Рекомендации: 1. **Визуализация:** Выполнить рентгенографию грудной клетки сейчас; при отклонениях — дальнейшее обследование. 2. **Фармакотерапия:** - Начать низкодозовый ингаляционный кортикостероид (например, флутиказон 100 µg дважды в сутки). - Обеспечить ингалятор с коротко действующим β₂-агонистом (альбутерол) для купирования приступов. 3. **Избегание триггеров:** Рекомендовать строгое избегание пассивного курения; держать окна закрытыми, когда сосед курит; рассмотреть очиститель воздуха. 4. **Боль в грудной стенке:** Лечить костохондрит НПВС (nonsteroidal anti-inflammatory drugs) (например, ибупрофен 400 mg трижды в сутки) и местным теплом; повторно оценить через 1–2 недели. 5. **Наблюдение:** Назначить контрольный визит к пульмонологу через 4–6 недель для оценки симптомов и повторной спирометрии для оценки ответа. 6. **Образ жизни:** Продолжать усилия по снижению массы тела; контролировать артериальное давление с учётом текущих антигипертензивных препаратов. 7. **Пересмотр лекарственной терапии:** Убедиться, что никакие другие препараты её схемы не способствуют кашлю; таковых не выявлено. 8. **Обучение пациентки:** Обучить правильной технике ингаляции, распознаванию ухудшения симптомов (усиление одышки, боль в груди в покое) и рекомендовать обратиться за неотложной помощью при их появлении. Примечания: Нет
A3: 2 | B3: Виньетка: Женщина 26 лет обратилась в клинику в связи с болью внизу живота в течение 3 дней. Срок беременности по датам — 18 недель. Пациентка описывает боль как острую, постоянную, распространяющуюся по нижним отделам живота с обеих сторон. Прошлой ночью впервые появились тошнота и рвота. Сегодня утром она не смогла удержать ни пищу, ни питьё. Вчера стул был нормальным. Она сообщает, что утром чувствовала озноб и дрожь, а затем ощущение жара; однако температуру не измеряла. Влагалищные кровотечения отрицает. Обзор систем органов: Общее состояние: Пациентка ощущает общую слабость и недомогание, но до 3 дней назад чувствовала себя как обычно. За время беременности прибавила примерно 5 lbs (2.3 kg). Кожа: Сыпь отрицает. ЛОР-органы и голова (HEENT): Отмечает сухость во рту. Головной боли, заложенности носа и боли в горле нет. Дыхательная система: Кашель и одышку отрицает. Сердечно-сосудистая система: Боль в грудной клетке и сердцебиение отрицает. Желудочно-кишечный тракт: Снижение аппетита в течение 1 дня; сегодня утром не смогла удержать ни пищу, ни питьё из-за тошноты и рвоты. Диареи и запора не было. Мочеполовая система: Отмечает учащённые позывы к мочеиспусканию и ощущение неполного опорожнения мочевого пузыря в течение последних 3 дней. Дизурии (dysuria) и гематурии (hematuria) нет. G1P0A0, регулярно наблюдается у акушера-гинеколога, проходит все плановые визиты и обследования. Влагалищного кровотечения нет. Костно-мышечная система: Отмечает умеренную разлитую боль в пояснице. Генерализованных мышечных болей нет. Неврологический статус: Без особенностей Психический статус: Без особенностей Анамнез жизни и заболеваний: Медицинский анамнез: Лёгкая интермиттирующая бронхиальная астма (asthma), диагностированная в детстве, требующая лишь эпизодического применения ингалятора для купирования приступов, госпитализаций по поводу астмы не было. В остальном здорова. Хирургический анамнез: Удаление зубов мудрости в возрасте 18 лет. Лекарственные препараты: Ингалятор с альбутеролом (albuterol) по потребности, примерно 1 раз в месяц. Ежедневно поливитамины для беременных. Аллергии: Известных лекарственных аллергий нет. Семейный анамнез: Мать здорова, 50 лет. Отец 53 лет, страдает артериальной гипертензией. Социальный анамнез: Пациентка работает инженером. Занимается физическими упражнениями 3 дня в неделю. Употребляла 2 бокала вина в неделю, но прекратила, узнав о беременности. Не курит, запрещённые вещества не употребляет. Недавних поездок не было. Моногамна, 1 половой партнёр мужского пола. Физикальное обследование: Общий вид: Правильно развитая женщина, выглядит уставшей и больной, но выраженного дистресса нет. Витальные показатели: Температура: 38.8° C Пульс: 120 beats/minute АД (blood pressure): 110/76 mm Hg Дыхание: 20/minute Кожа: Горячая, влажная от пота. Сыпи и цианоза нет. ЛОР-органы и голова (HEENT): Сухие слизистые оболочки, иктеричности склер и инъекции конъюнктивы нет, шея мягкая, лимфаденопатии нет. Дыхательная система: Дыхательные шумы одинаковы с обеих сторон, хорошее проведение воздуха во всех полях. Слева выслушиваются слабые инспираторные крепитирующие хрипы, более выраженные в базальных отделах. Свистящих хрипов нет. Сердечно-сосудистая система: Умеренная тахикардия с правильным ритмом; шумов, шума трения и ритма галопа нет. Периферических отёков нет. Желудочно-кишечный тракт: Кишечные шумы в норме. Живот мягкий, разлитая болезненность в нижних отделах с обеих сторон, без защитного напряжения, ригидности и симптомов раздражения брюшины. Болезненности в верхних квадрантах нет, беременная безболезненная матка на 2 cm ниже уровня пупка. Паховых и бедренных грыж нет. Ректальное исследование безболезненно, кал коричневый, реакция на скрытую кровь отрицательная. Мочеполовая система: Наружные половые органы без особенностей, болезненности при смещении шейки матки нет, скудные жидкие белые выделения из наружного зева шейки матки, зев закрыт. Сердцебиение плода ритмичное, 150 beats/minute. Костно-мышечная система: Отёка, болезненности и деформации суставов и конечностей нет. Положительный симптом поколачивания в области рёберно-позвоночного угла с обеих сторон. Неврологический статус: Без особенностей Психический статус: В сознании, ориентирована, речь беглая и связная. Результаты обследования: Результаты соответствующих исследований получены и показывают следующее: Кровь: Тест Результат Результаты (единицы СИ) Гемоглобин 12.5 g/dL 125 g/L Количество лейкоцитов (WBC) 17.0 x 103/µL 17.0 X 109/L Количество тромбоцитов 150 x 103/µL 150 X 109/L Базовый метаболический профиль: Тест Результат Результаты (единицы СИ) Натрий 137 mEq/L 137 mmol/L Калий 3.9 mEq/L 3.9 mmol/L Креатинин 0.7 mg/dL 62 micromol/L Глюкоза 78 mg/dL 4.3 mmol/L Мочевина крови (BUN) 23 mg/dL 8.2 mmol/L Моча: Тест Результат Лейкоцитарная эстераза Положительно Кровь Положительно Кетоны Положительно Бактерии Много Лейкоциты (WBCs) 30-50 в поле зрения при большом увеличении Нитриты Положительно Лейкоцитарная эстераза Положительно Белок Отрицательно Панель ИППП (STD) Гонорея/хламидиоз/трихомониаз в моче отрицательные Ультразвуковое исследование: УЗИ почек/мочевого пузыря: Гидронефроза не выявлено. Случайно выявлен внутриматочный плод с частотой сердцебиения 156 beats/minute. | C3: Острый пиелонефрит при беременности (Acute pyelonephritis in pregnancy) | D3: Требуется экстренная помощь | E3: Урология (Urology) | F3: молодой возраст (25-44) | G3: Возраст: 26 Пол: Женский Жалобы: Боль внизу живота с лихорадкой, тошнотой/рвотой и учащённым/императивным мочеиспусканием в течение 3 дней. Анализ: Пациентка находится на сроке 18 недель беременности и предъявляет жалобы при наличии лихорадки (38.8 °C), тахикардии (120 bpm), лейкоцитоза (лейкоциты 17 × 10³/µL) и выраженной пиурии с нитрит-положительной мочой, содержащей множество бактерий. Отмечается двусторонняя болезненность в области рёберно-позвоночного угла, симптомы дизурического типа и признаки обезвоживания (сухие слизистые оболочки, кетонурия). Эти данные классичны для острого пиелонефрита (acute pyelonephritis). При беременности пиелонефрит сопряжён с повышенным риском материнского сепсиса и страдания плода, в связи с чем требует срочной госпитализации и внутривенной терапии. Дифференциальные варианты (например, цистит, холецистит, аппендицит, акушерские осложнения) хуже согласуются с изменениями в моче, болезненностью в поясничной области и положительным посевом мочи. Необходимое диагностическое оборудование/исследования: - Посевы крови (до начала антибиотикотерапии) - Повторный посев мочи (для определения возбудителя и чувствительности) - Непрерывный мониторинг частоты сердечных сокращений плода (при госпитализации) - Динамический общий анализ крови (CBC) и базовый метаболический профиль для контроля ответа на лечение и функции почек Заключение: Острый пиелонефрит у женщины 26 лет на сроке 18 недель беременности, осложнённый обезвоживанием и системными признаками инфекции. Тип неотложности: Требуется экстренная помощь Субклиническая специализация: Акушерство и гинекология Рекомендации: 1. Госпитализировать для внутривенной (в/в) антибиотикотерапии, безопасной при беременности (например, цефтриаксон 1 g в/в ежедневно ± ампициллин 2 g в/в каждые 6 ч). 2. Начать активную в/в гидратацию для коррекции обезвоживания и кетонурии. 3. Выполнить посевы крови и повторный посев мочи до начала антибиотикотерапии. 4. Начать непрерывный мониторинг состояния плода; оценивать частоту сердечных сокращений и активность плода. 5. Контролировать витальные показатели, диурез, общий анализ крови и функцию почек каждые 12–24 ч. 6. При необходимости назначать жаропонижающие (парацетамол/ацетаминофен); избегать НПВС (nonsteroidal anti-inflammatory drugs) при беременности. 7. Обеспечить обезболивание при боли в поясничной области (например, ацетаминофен). 8. После нормализации температуры и клинического улучшения в течение ≥48 ч рассмотреть переход на пероральные антибиотики (например, амоксициллин-клавуланат) для завершения общего курса длительностью 10–14 дней. 9. Информировать пациентку о признаках рецидива и важности завершения курса антибиотиков. 10. Организовать акушерское наблюдение в течение 1 недели после выписки и повторный посев мочи для подтверждения эрадикации. Примечания: Нет. | H3: Возраст: 26 Пол: Женский Жалобы: 3-дневный анамнез острой постоянной боли внизу живота с тошнотой, рвотой и лихорадкой у женщины на сроке 18 недель беременности; сопутствующие мочевые симптомы и недавний озноб с документированной лихорадкой. Анализ: У пациентки острое лихорадочное заболевание во время беременности, характеризующееся болью внизу живота, тошнотой, рвотой, императивными позывами к мочеиспусканию и болезненностью в области рёберно-позвоночного угла. Витальные показатели демонстрируют высокую лихорадку (38.8°C) и тахикардию (120 bpm). Лабораторные данные выявляют лейкоцитоз (лейкоциты 17.0 x 10⁹/L), положительную лейкоцитарную эстеразу мочи, нитриты, бактерии, лейкоциты и кетонурию. Эти данные убедительно подтверждают диагноз острого пиелонефрита (acute pyelonephritis). Отсутствие влагалищного кровотечения, болезненности при смещении шейки матки и болезненности матки делает акушерские причины, такие как выкидыш, внематочная беременность или хориоамнионит, менее вероятными. Наличие системных симптомов, лихорадки и двусторонней болезненности в поясничной области при нормальном УЗИ почек (без обструкции) подтверждает диагноз пиелонефрита — частого и серьёзного осложнения беременности, обусловленного физиологическим расширением мочеточников. Дифференциальный ряд включает гастроэнтерит и аппендицит, однако изменения в моче, отсутствие диареи и двусторонняя болезненность в области рёберно-позвоночного угла делают их менее вероятными. Необходимое диагностическое оборудование/исследования: Нет Заключение: У пациентки острый пиелонефрит при беременности, вероятно бактериальной этиологии, на основании лихорадки, лейкоцитоза, мочевых симптомов, болезненности в области рёберно-позвоночного угла и общего анализа мочи, соответствующего инфекции. Тип неотложности: Требуется экстренная помощь Субклиническая специализация: Инфекционные болезни Рекомендации: Немедленная госпитализация для внутривенной антибиотикотерапии (например, цефтриаксон или ампициллин-гентамицин с коррекцией согласно местным рекомендациям и чувствительности культуры), инфузионная терапия при обезвоживании (о чём свидетельствуют сухие слизистые оболочки, кетонурия и невозможность перорального приёма) и тщательный мониторинг состояния плода. Посевы крови и мочи следует выполнить до начала антибиотикотерапии. Переход на пероральные антибиотики после клинического улучшения, как правило, через 48–72 часа без лихорадки. Амбулаторное наблюдение у акушера-гинеколога и уролога по показаниям. Обучение пациентки важности завершения лечения и распознаванию признаков преждевременных родов. Примечания: Пиелонефрит при беременности сопряжён с повышенным риском преждевременных родов, сепсиса и респираторных осложнений (например, ОРДС (acute respiratory distress syndrome)), что требует незамедлительного лечения. Двустороннее поражение не исключает пиелонефрит, особенно при беременности. Нормальное УЗИ почек исключает обструкцию, но не исключает инфекцию. | I3: Возраст: 26 Пол: Женский Жалобы: 3-дневный анамнез острой постоянной боли внизу живота с иррадиацией с обеих сторон, впервые возникшие тошнота и рвота, лихорадка, озноб, учащённое мочеиспускание и ощущение неполного опорожнения, двусторонняя болезненность в области рёберно-позвоночного угла. Анализ: Пациентка — женщина на сроке 18 недель беременности с лихорадкой (38.8°C), тахикардией (120 bpm), двусторонней болезненностью в рёберно-позвоночном углу (CVA) и общим анализом мочи с положительной лейкоцитарной эстеразой, нитритами, кровью, кетонами, множеством бактерий и 30-50 лейкоцитами в поле зрения при большом увеличении (HPF). Эти данные в высокой степени соответствуют острому пиелонефриту (acute pyelonephritis) при беременности. Отсутствие болезненности при смещении шейки матки, закрытый наружный зев шейки матки и нормальная частота сердечных сокращений плода свидетельствуют против преждевременных родов или воспалительных заболеваний органов малого таза. Дифференциальный ряд включает другие причины боли в животе при беременности (например, аппендицит, перекрут яичника, боль в круглой связке матки), однако изменения в моче и болезненность в рёберно-позвоночном углу убедительно указывают на инфекцию мочевыводящих путей, восходящую к почкам. У пациентки также имеется обезвоживание (сухие слизистые оболочки, кетонурия, невозможность удержать жидкость), она выглядит больной, с признаками системной инфекции. Беременность повышает риск осложнений пиелонефрита, включая сепсис, преждевременные роды и почечную дисфункцию, что требует срочного обследования и лечения. Необходимое диагностическое оборудование/исследования: Посевы крови, посев мочи с определением чувствительности, повторный общий анализ крови и базовый метаболический профиль, мониторинг частоты сердечных сокращений плода и непрерывный мониторинг витальных показателей. (Уже выполненное УЗИ почек/мочевого пузыря не выявило гидронефроза.) Заключение: Острый пиелонефрит у пациентки на сроке 18 недель беременности с обезвоживанием и системными симптомами, требующий госпитализации для внутривенной антибиотикотерапии, гидратации и мониторинга состояния плода. Тип неотложности: Требуется экстренная помощь Субклиническая специализация: Акушерство и гинекология Рекомендации: Госпитализировать пациентку для внутривенной инфузионной терапии и эмпирической внутривенной антибиотикотерапии (например, цефтриаксон или ампициллин плюс гентамицин с коррекцией с учётом беременности и функции почек). Выполнить посевы крови и мочи до начала антибиотикотерапии. Тщательно контролировать витальные показатели матери, диурез и частоту сердечных сокращений плода. При необходимости назначать противорвотные средства при тошноте/рвоте и корректировать обезвоживание. Повторно оценивать клинический ответ и корректировать антибиотики по результатам посевов. Рассмотреть консультацию акушера-гинеколога для дальнейшего ведения беременности. Информировать пациентку о тревожных признаках, таких как усиление боли, лихорадка, схватки или влагалищное кровотечение. Примечания: Беременность меняет выбор антибиотиков; избегать тетрациклинов и фторхинолонов. Наличие кетонов и невозможность удержать жидкость указывают на значительное обезвоживание, которое следует незамедлительно скорректировать. Частота сердечных сокращений плода обнадёживающая — 150-156 bpm, однако во время острого заболевания показан непрерывный мониторинг. | J3: Возраст: 26 Пол: Женский Жалобы: 3‑дневный анамнез острой, постоянной боли внизу живота с двусторонней иррадиацией, впервые возникшие тошнота/рвота, лихорадка, озноб и мочевые симптомы по типу дизурии у женщины на 18‑й неделе беременности. Анализ: У пациентки лихорадка (38,8 °C), тахикардия (120 уд/мин), лейкоцитоз (лейкоциты 17 ×10³/мкл), двусторонняя болезненность в рёберно‑позвоночном углу, сухость слизистых оболочек, кетонурия и общий анализ мочи с лейкоцитарной эстеразой (leukocyte esterase), нитритами, обильной бактериальной флорой и пиурией. Эти данные соответствуют критериям ССВО (systemic inflammatory response syndrome) и классичны для острого пиелонефрита, особенно при беременности, где индуцированный прогестероном стаз мочи заметно повышает риск. Нормальное ультразвуковое исследование почек/мочевого пузыря исключает гидронефроз или обструктивную уропатию, но не исключает инфекцию. Отсутствие болезненности при смещении шейки матки, влагалищного кровотечения или болезненности матки делает акушерские инфекции (например, хориоамнионит) менее вероятными. В дифференциальный ряд входят инфекция нижних мочевых путей (цистит), почечные конкременты, аппендицит, перекрут яичника и ранние преждевременные роды; однако сочетание системных признаков, болезненности в рёберно‑позвоночном углу и положительных результатов исследования мочи убедительно свидетельствует в пользу острого пиелонефрита. Необходимое диагностическое оборудование/исследования: - Посев мочи с определением чувствительности (до антибиотиков) - Посевы крови (до антибиотиков) - Уровень лактата в сыворотке - Повторный общий анализ крови с лейкоцитарной формулой - Базовая метаболическая панель (включая электролиты, мочевину крови (BUN), креатинин) - Мониторинг частоты сердечных сокращений плода (нестрессовый тест или непрерывный электронный мониторинг плода) - Терапевтический лекарственный мониторинг при применении гентамицина (пиковые/остаточные уровни) Заключение: Острый пиелонефрит при беременности во втором триместре (осложнённая инфекция мочевых путей). Тип неотложности: Требуется экстренная помощь Субклиническая специализация: Акушерство и гинекология Рекомендации: 1. Госпитализация в акушерское отделение для стационарного ведения. 2. Начать активную инфузионную терапию внутривенно (например, изотоническим кристаллоидом) для коррекции обезвоживания и кетоза. 3. Начать эмпирическую внутривенную антибиотикотерапию, безопасную при беременности, например цефтриаксон + ампициллин или цефотаксим ± гентамицин, корректируя дозы по функции почек и избегая тератогенных препаратов (фторхинолоны, тетрациклины). 4. Взять все посевы (моча, кровь) **до** введения антибиотиков. 5. Обеспечить жаропонижающие (парацетамол) и обезболивание по потребности с наблюдением за обострением астмы. 6. Непрерывный мониторинг витальных показателей матери и частоты сердечных сокращений плода на протяжении всей терапии. 7. Повторно оценить клиническое состояние через 48–72 часа; при сохранении лихорадки или отсутствии клинического улучшения рассмотреть повторную визуализацию почек для выявления абсцесса или скрытой обструкции. 8. После нормализации температуры в течение ≥24 часов перейти на пероральные антибиотики с учётом чувствительности по посеву для завершения общего курса длительностью 10‑14 дней. 9. Организовать акушерское наблюдение для контроля роста плода и провести консультирование по достаточной гидратации, раннему распознаванию мочевых симптомов и скринингу бессимптомной бактериурии при последующих беременностях. 10. При применении гентамицина определять концентрацию препарата в сыворотке для терапевтического мониторинга во избежание нефро‑ и ототоксичности. Примечания: - Обезвоживание очевидно (сухость слизистых, повышение мочевины крови (BUN), кетонурия) и должно быть безотлагательно скорректировано. - Пиелонефрит у матери повышает риск преждевременных родов, низкой массы тела при рождении и сепсиса; продолжающийся мониторинг плода необходим. - Незначительные инспираторные хрипы могут отражать ателектаз или ранние жидкостные сдвиги; следить за респираторным статусом. - Лёгкая интермиттирующая астма не является противопоказанием, но следует помнить о возможных лекарственных взаимодействиях. - Отсутствие гидронефроза по данным ультразвукового исследования не изменяет необходимости стационарного лечения.
A4: 3 | B4: Виньетка: Женщина 53 лет обратилась в поликлинику по поводу сердцебиения (palpitations). Она является постоянной пациенткой этого учреждения, в анамнезе — хорошо контролируемая артериальная гипертензия (hypertension), сахарный диабет 2 типа и головные боли напряжения (tension headaches). Она сообщает, что на протяжении последних 2 мес отмечает перемежающееся сердцебиение. Она описывает эпизоды как ощущение неритмичного и учащённого сердцебиения, сопровождающегося утомляемостью. Она отрицает боль в грудной клетке, одышку, головокружение и синкопе (syncope). Эпизоды длятся от 10 мин до нескольких часов, возникают один-два раза в нед и разрешаются самостоятельно. Последний эпизод был 3 дня назад. Она не может выявить какие-либо определённые провоцирующие факторы. В целом активна, проходит пешком 3 мили несколько дней в нед без каких-либо симптомов при нагрузке, включая боль в грудной клетке и диспноэ (dyspnea). Семейный анамнез по раннему развитию сердечных заболеваний или внезапной смерти не отягощён. Отрицает недавнюю лихорадку или инфекционные симптомы. Обзор систем: Общее состояние: Пациентка в целом чувствовала себя хорошо. Кожа: Новых высыпаний или кожных образований нет. ЛОР-органы и голова (HEENT): Изменений зрения, боли в ушах, назальных симптомов или боли в горле нет. Дыхательная система: Отрицает одышку, диспноэ при нагрузке и кашель. Сердечно-сосудистая система: Ортопноэ (orthopnea), пароксизмальной ночной одышки (paroxysmal nocturnal dyspnea) или отёков нижних конечностей нет. Желудочно-кишечный тракт: Отрицает боль в животе и снижение аппетита. Мочеполовая система: Без особенностей Репродуктивная система: Без особенностей Костно-мышечная система: Недавних травм нет. Нервная система: Без особенностей Психический статус: В целом в хорошем расположении духа; крайних колебаний настроения нет. Анамнез заболеваний: Медицинский анамнез: Артериальная гипертензия, сахарный диабет 2 типа и головные боли напряжения. Хирургический анамнез: Аппендэктомия (appendectomy) в возрасте 20 лет. Лекарственные препараты: Лизиноприл 10 mg ежедневно и метформин 500 mg 2 раза в сут (bid). Аллергии: Известных лекарственных аллергий нет. Семейный анамнез: Мать жива, страдает артериальной гипертензией и сахарным диабетом. Отец умер от рака лёгкого. Анамнеза раннего развития ишемической болезни сердца (coronary artery disease) или внезапной сердечной смерти нет. Социальный анамнез: Пациентка замужем, работает школьной учительницей. Регулярно занимается физическими упражнениями 3 раза в нед. Курения в анамнезе нет. Выпивает бокал вина за ужином большинство вечеров и одну чашку кофе каждое утро. Отрицает применение деконгестантов, кокаина и других стимуляторов. Употребления запрещённых наркотиков нет. Физикальное обследование: Общий вид: Худощавая женщина среднего возраста без явных признаков дистресса. Витальные показатели: Температура: 37.2° C Пульс: 58 уд/мин АД (blood pressure): 125/74 mm Hg Дыхание: 14/мин Сатурация кислорода: 96% при дыхании атмосферным воздухом Кожа: Высыпаний не отмечено. ЛОР-органы и голова (HEENT): Ротоглотка чистая. Дыхательная система: При аускультации лёгкие чистые с обеих сторон. Свистящих хрипов, сухих хрипов и влажных хрипов нет. Сердечно-сосудистая система: Ритм и частота правильные, нормальные S1 и S2; шумов, шума трения и ритма галопа нет. Быстрый подъём пульсовой волны на сонных артериях. Набухания яремных вен нет. Желудочно-кишечный тракт: Живот мягкий, безболезненный, не вздут; кишечные шумы выслушиваются. Мочеполовая система: Без особенностей Костно-мышечная система: Без особенностей Нервная система: Без особенностей Психический статус: Без особенностей | C4: Фибрилляция предсердий (Atrial fibrillation) | D4: Требуется неэкстренная помощь | E4: Кардиология (Cardiology) | F4: средний возраст (45-60) | G4: Возраст: 53 года Пол: Женский Жалобы: Перемежающееся сердцебиение (palpitations), описываемое как неритмичные и учащённые сердечные сокращения с сопутствующей утомляемостью на протяжении последних 2 месяцев. Анализ: Пациентка сообщает об эпизодическом сердцебиении длительностью от 10 минут до нескольких часов, возникающем один-два раза в неделю, со спонтанным разрешением и без сопутствующей боли в грудной клетке, одышки, головокружения или синкопе (syncope). У неё хорошо контролируемые артериальная гипертензия и сахарный диабет 2 типа, но нет симптомов при нагрузке, нет семейного анамнеза раннего развития сердечных заболеваний или внезапной смерти, а сердечно-сосудистое обследование в норме с правильными частотой и ритмом. Перемежающийся характер и отсутствие нарушений гемодинамики или настораживающих симптомов указывают на возможную пароксизмальную аритмию (например, фибрилляцию предсердий (atrial fibrillation), трепетание предсердий или наджелудочковую тахикардию) либо доброкачественную эктопию, однако ощущение «неритмичного и учащённого» сердцебиения вызывает настороженность в отношении фибрилляции предсердий. Дифференциально-диагностические соображения включают гипертиреоз, электролитные нарушения, анемию и эффекты лекарственных препаратов, хотя её текущие препараты (лизиноприл, метформин) не являются типичными аритмогенными триггерами. Отсутствие симптомов структурной патологии сердца и нормальные данные осмотра снижают вероятность значимой лежащей в основе кардиомиопатии, но с учётом эпизодического характера необходимо амбулаторное мониторирование для регистрации аритмии. Необходимое диагностическое оборудование/исследования: ЭКГ (electrocardiogram) в 12 отведениях; амбулаторное кардиомониторирование (30-дневный событийный монитор или холтеровское мониторирование, с учётом того, что эпизоды возникают 1–2 раза в неделю); исследование функции щитовидной железы (ТТГ (thyroid-stimulating hormone), свободный Т4); общий анализ крови; базовая метаболическая панель (электролиты, функция почек); рассмотреть эхокардиографию при подтверждении аритмии или при подозрении на структурную патологию сердца. Заключение: Женщина 53 лет с артериальной гипертензией и сахарным диабетом 2 типа обратилась с перемежающимся, самокупирующимся сердцебиением без настораживающих симптомов или патологических данных физикального обследования. Клиническая картина соответствует возможной пароксизмальной аритмии, наиболее вероятно фибрилляции предсердий, что требует амбулаторного мониторирования и базовой лабораторной оценки для подтверждения диагноза и исключения вторичных причин. Она гемодинамически стабильна и не нуждается в неотложном вмешательстве. Тип неотложности: Требуется неэкстренная помощь Субклиническая специализация: Кардиология Рекомендации: Выполнить исходную ЭКГ (electrocardiogram) в 12 отведениях для оценки исходных нарушений ритма или признаков перенесённой ишемии. Начать амбулаторное кардиомониторирование (предпочтительно 30-дневный событийный монитор или холтеровское мониторирование) для регистрации эпизодического сердцебиения и сопоставления симптомов с ритмом. Назначить исследование функции щитовидной железы, общий анализ крови и базовую метаболическую панель для оценки гипертиреоза, анемии или электролитных нарушений. Рекомендовать пациентке вести дневник симптомов во время мониторирования с указанием времени, продолжительности и сопутствующих симптомов. При подтверждении фибрилляции предсердий оценить риск инсульта (например, по шкале CHA2DS2-VASc) с учётом её артериальной гипертензии и сахарного диабета и рассмотреть антикоагуляцию и стратегии контроля частоты/ритма. Обратить внимание на факторы образа жизни: рекомендовать умеренность в отношении кофеина (в настоящее время одна чашка кофе в день) и алкоголя (бокал вина большинство вечеров), поскольку и то и другое может провоцировать сердцебиение. Успокоить пациентку, что неотложное вмешательство не требуется с учётом отсутствия синкопе, боли в грудной клетке или гемодинамической нестабильности, но запланировать повторный визит после получения результатов мониторирования. Примечания: Нет | H4: Возраст: 53 Пол: Женский Жалобы: Перемежающееся сердцебиение (palpitations) с сопутствующей утомляемостью, длительностью от 10 минут до нескольких часов, возникающее 1–2 раза в неделю. Анализ: Пациентка — женщина среднего возраста с хорошо контролируемыми артериальной гипертензией и сахарным диабетом, сообщающая об эпизодических ощущениях неритмичного, учащённого сердцебиения. Она гемодинамически стабильна (АД (blood pressure) 125/74 mm Hg, ЧСС (heart rate) 58 уд/мин в покое), отрицает боль в грудной клетке, одышку, синкопе (syncope) или ограничение переносимости нагрузки. Физикальное обследование показывает правильный ритм на момент оценки, что делает сердцебиение пароксизмальным. Дифференциальный диагноз включает пароксизмальную наджелудочковую тахикардию (например, АВ-узловую реципрокную тахикардию), предсердные тахиаритмии (пароксизмальную фибрилляцию/трепетание предсердий), предсердную или желудочковую экстрасистолию и метаболические причины, такие как гипертиреоз или электролитные нарушения. Отсутствие стимуляторов, структурной патологии сердца при осмотре и нормальная ЭКГ (electrocardiogram) покоя (подлежит выполнению) делают первичную аритмическую этиологию наиболее вероятной. Необходимое диагностическое оборудование/исследования: - ЭКГ (electrocardiogram) покоя в 12 отведениях (исходная) - Амбулаторное кардиомониторирование (24–48 ч холтеровское мониторирование или событийный регистратор) для регистрации эпизода - Лабораторные исследования: ТТГ (thyroid-stimulating hormone), ОАК (complete blood count), базовая метаболическая панель (электролиты, функция почек), глюкоза натощак/HbA1c - Рассмотреть трансторакальную эхокардиографию при документированной аритмии или при подозрении на структурную патологию сердца Заключение: Стабильная пациентка с пароксизмальным сердцебиением, вероятно обусловленным перемежающейся наджелудочковой тахиаритмией; для постановки диагноза необходимы дальнейшее мониторирование сердечного ритма и базовые метаболические/эндокринные лабораторные исследования. Тип неотложности: Требуется неэкстренная помощь Субклиническая специализация: Кардиология Рекомендации: 1. Выполнить ЭКГ (electrocardiogram) покоя в 12 отведениях во время визита. 2. Организовать амбулаторное мониторирование ритма (холтеровское мониторирование или событийный регистратор) для документирования аритмии во время симптомов. 3. Назначить лабораторные исследования (ТТГ (thyroid-stimulating hormone), ОАК (complete blood count), БМП (basic metabolic panel), глюкоза натощак/HbA1c) для исключения метаболических факторов. 4. При подтверждении нарушения ритма направить к кардиологу для возможного электрофизиологического обследования и обсуждения вариантов лечения (например, бета-блокатор, блокатор кальциевых каналов или катетерная аблация). 5. Проконсультировать пациентку по мерам образа жизни: ограничить потребление кофеина/алкоголя, поддерживать достаточную гидратацию и продолжать регулярные физические нагрузки по переносимости. 6. Обеспечить оптимальный контроль артериальной гипертензии и сахарного диабета; на повторном визите проанализировать дневники артериального давления и глюкозы. Примечания: Нет. | I4: Возраст: 53 Пол: Женский Жалобы: Перемежающиеся сердцебиения, описываемые как нерегулярные, учащённые, длительностью от 10 минут до нескольких часов, сопровождающиеся утомляемостью, возникающие 1–2 раза в неделю без боли в груди, одышки, синкопе или ограничения переносимости нагрузки. Анализ: Пациентка гемодинамически стабильна (АД (blood pressure) 125/74 мм рт. ст., ЧСС (heart rate) 58 уд/мин, нормальный осмотр) и имеет сердечно-сосудистые факторы риска (артериальная гипертензия, сахарный диабет 2 типа), которые повышают вероятность фибрилляции предсердий (atrial fibrillation, AF). Эпизоды пароксизмальные, нерегулярные и самокупирующиеся, что соответствует пароксизмальным наджелудочковым аритмиям — прежде всего пароксизмальной фибрилляции предсердий (paroxysmal atrial fibrillation, PAF) или пароксизмальной наджелудочковой тахикардии (paroxysmal supraventricular tachycardia, PSVT). Отсутствие структурного заболевания сердца при осмотре, нормальная частота сердечных сокращений в покое и отсутствие симптомов «красных флагов» делают неотложную аритмию маловероятной. Дифференциально-диагностические соображения включают: * Пароксизмальную фибрилляцию предсердий / трепетание предсердий * Пароксизмальную наджелудочковую тахикардию (АВУРТ/АВРТ, AVNRT/AVRT) * Преждевременные предсердные или желудочковые сокращения * Гипертиреоз, электролитные нарушения, анемию или другие метаболические триггеры * Употребление кофеина/алкоголя, перименопаузальные гормональные изменения, автономную невропатию вследствие диабета и нарушения дыхания во сне как обратимые способствующие факторы Основной рабочий диагноз — пароксизмальная наджелудочковая аритмия, при этом PAF является ведущей возможностью с учётом возраста и профиля риска пациентки, тогда как PSVT остаётся правдоподобной альтернативой. Необходимое диагностическое оборудование/исследования: * Электрокардиограмма в покое в 12 отведениях (ECG) * Амбулаторное мониторирование ритма (24–48 ч холтеровское мониторирование или регистратор событий) * Трансторакальная эхокардиография (для оценки структуры и функции сердца) * Лабораторная панель: общий анализ крови (CBC), расширенная метаболическая панель (включая электролиты), HbA1c, тиреотропный гормон (TSH) * Рассмотреть скрининг нарушений дыхания во сне при возникновении клинического подозрения Заключение: У 53-летней женщины с перемежающимися нерегулярными сердцебиениями и сердечно-сосудистыми факторами риска наиболее вероятна пароксизмальная наджелудочковая аритмия, вероятнее всего пароксизмальная фибрилляция предсердий, хотя PSVT нельзя исключить. Она гемодинамически стабильна и не нуждается в экстренной помощи, но нуждается в своевременном амбулаторном кардиологическом обследовании и диагностическом обследовании. Тип неотложности: Требуется неэкстренная помощь Субклиническая специализация: Кардиология Рекомендации: 1. **Направление к кардиологу амбулаторно** в течение 1–2 недель для всестороннего обследования. 2. **Диагностическое обследование** в объёме, указанном выше (ЭКГ (electrocardiogram) в покое, амбулаторное мониторирование, эхокардиография, лабораторные исследования). 3. **Консультирование по образу жизни:** * Ограничить потребление кофеина и алкоголя (в настоящее время вино каждый вечер и кофе каждое утро). * Поддерживать регулярные аэробные нагрузки (продолжать ходьбу по 3 мили несколько раз в неделю). * Достичь оптимального контроля массы тела и управления стрессом. 4. **Пересмотр медикаментозной терапии:** Подтвердить, что лизиноприл и метформин не вносят вклад; препаратов, удлиняющих интервал QT, нет. 5. **Оценка триггеров:** Рекомендовать ведение дневника симптомов для сопоставления эпизодов с активностью, питанием или стрессорами. 6. **Рассмотреть пробное назначение бета-блокатора в низкой дозе (например, метопролола)** только после документирования ритма, если эпизоды частые и переносимые, с учётом того, что мнения экспертов по этому пункту различались. 7. **Если фибрилляция предсердий подтверждена:** * Рассчитать балл CHA₂DS₂‑VASc (возраст 53 = 0, артериальная гипертензия = 1, диабет = 1 → всего 2). * Начать антикоагулянтную терапию прямым пероральным антикоагулянтом при отсутствии противопоказаний. * Обсудить стратегии контроля частоты и контроля ритма на основании выраженности симптомов и предпочтений пациентки. 8. **Обучение пациентки:** Рекомендовать немедленно обратиться за медицинской помощью при появлении новой боли в груди, синкопе, тяжёлой одышки или выраженных сердцебиений. Примечания: Нет. | J4: Возраст: 53 Пол: Женский Жалобы: Перемежающееся сердцебиение (palpitations), описываемое как неритмичные и учащённые сердечные сокращения, длительностью от 10 минут до нескольких часов, возникающее один-два раза в неделю на протяжении последних 2 месяцев, сопровождающееся утомляемостью, но без боли в грудной клетке, одышки, головокружения или синкопе (syncope). Анализ: У пациентки классические симптомы пароксизмального сердцебиения, указывающие на аритмию, наиболее вероятно — пароксизмальную наджелудочковую тахикардию (paroxysmal supraventricular tachycardia) или фибрилляцию предсердий (atrial fibrillation), с учётом описания неритмичного и учащённого сердцебиения. Отсутствие симптомов структурной патологии сердца (например, ортопноэ, ПНО (PND), отёков), сохранённая переносимость физической нагрузки и отсутствие особенностей при сердечно-сосудистом обследовании снижают вероятность значимой структурной патологии сердца. Однако её возраст и сопутствующие заболевания (артериальная гипертензия, сахарный диабет) повышают риск фибрилляции предсердий. Текущий пульс 58 уд/мин находится в пределах нормы, но может отражать исходный синусовый ритм с перемежающейся тахиаритмией. Эпизодический, самокупирующийся характер и отсутствие нарушений гемодинамики указывают на стабильное состояние. Дифференциальный диагноз включает синусовую тахикардию, фибрилляцию предсердий с быстрым желудочковым ответом, трепетание предсердий или пароксизмальную наджелудочковую тахикардию. Тиреотоксикоз, употребление стимуляторов и электролитные нарушения менее вероятны с учётом отсутствия системных симптомов, нормальных витальных показателей и отсутствия анамнеза употребления стимуляторов. Необходимое диагностическое оборудование/исследования: Амбулаторное ЭКГ (electrocardiogram)-мониторирование (например, 24–48-часовое холтеровское мониторирование или событийный регистратор), уровень ТТГ (thyroid-stimulating hormone), базовая метаболическая панель. Заключение: Женщина 53 лет с хорошо контролируемыми артериальной гипертензией и сахарным диабетом обратилась с рецидивирующими, самокупирующимися эпизодами сердцебиения, указывающими на пароксизмальную аритмию. Данных за структурную патологию сердца или гемодинамическую нестабильность нет. Тип неотложности: Требуется неэкстренная помощь Субклиническая специализация: Кардиология Рекомендации: Начать амбулаторное ЭКГ (electrocardiogram)-мониторирование для регистрации аритмии во время симптомных эпизодов. Назначить ТТГ (thyroid-stimulating hormone) и электролиты для исключения метаболических или тиреоидных причин. Продолжить текущие препараты (лизиноприл, метформин) в назначенном режиме. Проконсультировать пациентку об избегании потенциальных триггеров, таких как кофеин и алкоголь, несмотря на низкую вероятность их причинной роли. Запланировать повторный визит к врачу первичного звена или кардиологу для рассмотрения результатов мониторирования. При подтверждении аритмии будут определены дальнейшая оценка риска инсульта (например, шкала CHA2DS2-VASc) и необходимость контроля частоты или ритма. Примечания: Отсутствие симптомов во время визита в поликлинику ограничивает немедленную постановку диагноза; поэтому амбулаторное мониторирование необходимо для сопоставления симптомов с сердечным ритмом.
A5: 4 | B5: Клинический случай: Девочку 3 лет приводит мать с жалобами на субфебрильную температуру 37,8 °C и мелкие пузырьки, замеченные на кистях и стопах с сегодняшнего утра. Мать также отмечает несколько мелких язвочек во рту у ребёнка. Ребёнок хорошо ест и пьёт, хотя несколько более капризен, чем обычно. У нескольких детей в её детском саду были похожие симптомы. При осмотре — рассеянные мелкие везикулы (vesicles) на ладонях, подошвах и несколько на тыльной поверхности кистей. На слизистой оболочке щёк видны две поверхностные язвы. Ребёнок в ясном сознании, активен, гидратация достаточная. | C5: Болезнь «рука-нога-рот» (Hand-foot-mouth disease), лёгкая форма | D5: Достаточно самопомощи | E5: Инфекционные болезни (Infectious Disease) | F5: дети (<15) | G5: Возраст: 3 года Пол: женский Жалобы: Субфебрильная температура с мелкими везикулами (vesicles) на кистях, стопах и язвами полости рта. Анализ: У ребёнка отмечаются лёгкая лихорадка (37,8 °C) и характерные везикулёзные высыпания на ладонях, подошвах, тыле кистей и поверхностные язвы слизистой оболочки щёк. Вспышка среди сверстников в детском саду убедительно указывает на контагиозную вирусную экзантему, наиболее соответствующую болезни «рука-нога-рот» (hand-foot-and-mouth disease, HFMD), вызванной вирусом Коксаки (coxsackievirus) A16 или энтеровирусом 71. Ребёнок в ясном сознании, активен, гидратация достаточная, сохраняет пероральный приём пищи, что указывает на отсутствие обезвоживания или системного поражения. Основные дифференциальные диагнозы (герпангина (herpangina), ветряная оспа (varicella), импетиго (impetigo), аллергический контактный дерматит (allergic contact dermatitis)) менее вероятны с учётом распределения (ладони/подошвы) и одновременных высыпаний в полости рта. Признаков осложнений (например, неврологических, кардиальных, тяжёлого обезвоживания) нет. Необходимое диагностическое оборудование/исследования: Не требуются Заключение: Классическая болезнь «рука-нога-рот» — доброкачественное самоограничивающееся вирусное заболевание. Тип неотложности: Достаточно самопомощи Субклиническая специализация: Педиатрия Рекомендации: 1. **Поддерживающая терапия** — поощрять продолжение приёма жидкости внутрь; предлагать прохладную мягкую пищу; контролировать объём потребления. 2. **Лихорадка/комфорт** — использовать соответствующие возрасту жаропонижающие (например, парацетамол (acetaminophen) или ибупрофен (ibuprofen)) при лихорадке или дискомфорте. 3. **Местное облегчение** — рассмотреть полоскания рта охлаждённой водой или мягким анальгетическим ополаскивателем, если ребёнок переносит. 4. **Гигиена и изоляция** — не водить ребёнка в детский сад, пока все высыпания не покроются корочками (обычно 5-7 дней); практиковать частое мытьё рук и дезинфицировать общие поверхности. 5. **Наблюдение** — следить за признаками обезвоживания, высокой лихорадкой, усилением боли или новыми неврологическими симптомами (например, вялость, судороги). При их появлении незамедлительно обратиться за медицинской помощью. 6. **Обучение родителей** — успокоить, что заболевание самоограничивающееся; объяснить типичное течение (7-10 дней) и низкий риск серьёзных осложнений. Примечания: Нет | H5: Возраст: 3 года Пол: Женский Жалобы: Субфебрильная лихорадка с мелкими везикулами на ладонях, подошвах, тыле кистей и поверхностными язвами в полости рта. Анализ: У ребёнка классическая триада заболевания «рука-нога-рот» (Hand-Foot-and-Mouth Disease, HFMD): субфебрильная лихорадка, везикулёзные высыпания на кистях/стопах и язвы в полости рта. Условия вспышки (множественные контакты в детском саду) убедительно поддерживают энтеровирусную этиологию, чаще всего вирус Коксаки A16 (Coxsackievirus A16) или энтеровирус 71 (Enterovirus 71). Ребёнок в ясном сознании, активен, хорошо гидратирован и переносит приём жидкости, что указывает на лёгкое, самоограничивающееся течение. Основные дифференциальные диагнозы, которые следует рассмотреть, — герпангина (herpangina), ветряная оспа (varicella), герпетический гингивостоматит (herpes simplex gingivostomatitis), многоформная эритема (erythema multiforme), импетиго (impetigo), герпетиформная экзема Капоши (eczema herpeticum), синдром Стивенса-Джонсона (Stevens-Johnson syndrome), аллергический контактный дерматит (allergic contact dermatitis), атипичные энтеровирусные инфекции — менее вероятны с учётом распределения высыпаний, отсутствия системной токсичности и эпидемиологического контекста. Необходимое диагностическое оборудование/исследования: Нет Заключение: Классическое заболевание «рука-нога-рот» у 3-летнего ребёнка в удовлетворительном состоянии; целесообразно амбулаторное поддерживающее лечение. Тип неотложности: Требуется неэкстренная помощь Субклиническая специализация: Педиатрия Рекомендации: 1. **Поддерживающая терапия** – Поощрять приём жидкости внутрь (вода, растворы для оральной регидратации, прозрачные супы). Предлагать мягкую, прохладную пищу; избегать кислых или острых продуктов, которые могут раздражать высыпания в полости рта. 2. **Облегчение симптомов** – Назначить соответствующие возрасту парацетамол (acetaminophen) или ибупрофен (ibuprofen) при лихорадке и дискомфорте. Местные анальгетики для полости рта (например, лидокаин) могут применяться с осторожностью; избегать у детей, которые не могут надёжно сплёвывать, из-за риска аспирации. 3. **Наблюдение за тревожными признаками (red-flag signs)** – Обучить лиц, осуществляющих уход, обращаться за неотложной помощью при появлении любого из следующего: лихорадка > 39 °C, признаки обезвоживания (сухость слизистых, снижение диуреза, вялость), невозможность глотать жидкость, судороги, быстрое распространение сыпи за пределы кистей/стоп, дыхательная недостаточность или признаки вторичной бактериальной инфекции. 4. **Инфекционный контроль** – Строгая гигиена рук, регулярная дезинфекция игрушек и поверхностей, отказ от совместного использования столовых приборов. Не водить ребёнка в детский сад до разрешения лихорадки и покрытия высыпаний корочками (примерно 5–7 дней). 5. **Проверка вакцинации/иммунизации** – Уточнить статус иммунизации против ветряной оспы, чтобы помочь исключить ветряную оспу. 6. **Консультирование о редких осложнениях** – Обсудить, что энтеровирус 71 в редких случаях может вызывать неврологическое или кардиопульмональное заболевание; при появлении неврологических симптомов (например, вялость, миоклонус) или дыхательных нарушений необходима незамедлительная оценка. 7. **Особые группы населения** – Рекомендовать беременным контактным лицам при экспозиции обратиться к акушеру, поскольку сообщалось о редких воздействиях на плод. 8. **Динамическое наблюдение** – Плановый повторный осмотр через 2–3 дня для переоценки гидратации и динамики симптомов; антибиотики или противовирусные препараты не показаны, если не выявлена вторичная бактериальная инфекция. Примечания: Наблюдать за обезвоживанием и тревожными признаками; рассмотреть наличие иммунодефицита или хронического заболевания, если течение становится атипичным или затяжным. Нет. | I5: Возраст: 3 года Пол: женский Жалобы: Субфебрильная температура, язвы полости рта и мелкие пузырьки на кистях и стопах у девочки 3 лет с недавним контактом с аналогичными случаями в детском саду. Анализ: Клиническая картина соответствует болезни «рука-нога-рот» (hand, foot, and mouth disease, HFMD) — распространённому вирусному заболеванию у детей раннего возраста, вызываемому энтеровирусами, наиболее часто вирусом Коксаки (coxsackievirus) A16. Ключевые находки, поддерживающие этот диагноз, включают наличие субфебрильной температуры, язв на слизистой оболочке щёк и везикулёзных (vesicular) высыпаний на ладонях и подошвах, а также анамнез аналогичных случаев в детском саду, что указывает на вероятную передачу. Гидратация ребёнка достаточная, сознание ясное, ребёнок активен, что поддерживает лёгкое неосложнённое течение. Дифференциальные диагнозы включают герпангину (herpangina) (которая преимущественно затрагивает высыпания в полости рта), герпетический гингивостоматит (herpetic gingivostomatitis) (обычно более тяжёлый, с более высокой лихорадкой и поражением дёсен) и другие вирусные экзантемы, однако распределение кожных высыпаний и лёгкие системные симптомы говорят в пользу HFMD. Необходимое диагностическое оборудование/исследования: Не требуются Заключение: У ребёнка классические признаки и симптомы болезни «рука-нога-рот», вероятно вирусного происхождения, без признаков осложнений или обезвоживания. Тип неотложности: Достаточно самопомощи Субклиническая специализация: Педиатрия Рекомендации: Показана поддерживающая терапия. Поощрять приём жидкости внутрь для поддержания гидратации; предлагать прохладную мягкую пищу и избегать кислых или солёных продуктов, которые могут раздражать язвы полости рта. При дискомфорте или лихорадке по потребности можно использовать парацетамол (acetaminophen) или ибупрофен (ibuprofen). Наблюдать за признаками обезвоживания (например, снижение диуреза, сухость слизистых оболочек, вялость) или ухудшением симптомов. Ребёнка следует не водить в детский сад до нормализации температуры и начала разрешения высыпаний для снижения передачи. Успокоить лицо, осуществляющее уход, что заболевание обычно самоограничивающееся и разрешается в течение 7–10 дней. Примечания: Нет | J5: Возраст: 3 года Пол: женский Жалобы: Субфебрильная температура (37,8 °C) с мелкими пузырьками на кистях и стопах и несколькими мелкими язвочками во рту. Анализ: Сочетание субфебрильной температуры, везикулёзных (vesicular) высыпаний на ладонях, подошвах и тыле кистей, а также поверхностных язв полости рта у ребёнка раннего возраста с известным контактом в детском саду с аналогичными симптомами весьма характерно для болезни «рука-нога-рот» (Hand, Foot, and Mouth Disease, HFMD), наиболее часто вызываемой вирусом Коксаки (Coxsackievirus) (например, A16 или энтеровирусом 71). Ребёнок в ясном сознании, активен, гидратация достаточная, хорошо ест и пьёт, что указывает на лёгкое неосложнённое течение. Дифференциально-диагностические соображения включают герпангину (herpangina) (язвы полости рта без сыпи на конечностях), ветряную оспу (chickenpox) (более генерализованная, центростремительная везикулёзная сыпь) и другие вирусные экзантемы, однако классическое распределение по ладоням и подошвам убедительно поддерживает HFMD. Необходимое диагностическое оборудование/исследования: Не требуются (клинический диагноз; при типичном неосложнённом случае лабораторные или визуализирующие исследования не нужны). Заключение: Классическая лёгкая болезнь «рука-нога-рот» (HFMD) у ребёнка с удовлетворительным общим состоянием и достаточной гидратацией, самоограничивающееся вирусное заболевание. Тип неотложности: Достаточно самопомощи Субклиническая специализация: Педиатрия Рекомендации: Обеспечить поддерживающую терапию на дому: достаточное поступление жидкости внутрь для поддержания гидратации, предлагать мягкую прохладную пищу и избегать кислых или солёных продуктов, которые могут раздражать язвы полости рта, использовать жаропонижающие (например, парацетамол (acetaminophen) или ибупрофен (ibuprofen) в дозе по массе тела) при лихорадке или дискомфорте. Успокоить мать, что заболевание самоограничивающееся и обычно разрешается в течение 7–10 дней. Рекомендовать оставить ребёнка дома, не водить в детский сад, пока везикулы не подсохнут и не нормализуется температура, чтобы предотвратить распространение. Наблюдать за признаками обезвоживания (снижение диуреза, сухость во рту, вялость) или осложнениями, такими как высокая лихорадка, раздражительность или неврологические симптомы, и при их появлении обратиться за медицинской помощью. Примечания: Хотя это редко, энтеровирус 71 может вызывать тяжёлые осложнения (например, менингит, энцефалит); родителям следует разъяснить необходимость повторного обращения для оценки, если у ребёнка появятся стойкая высокая лихорадка, вялость, плохое питание или неврологические признаки. Соблюдать хорошую гигиену рук для ограничения распространения в семье.
A6: 5 | B6: Клиническая ситуация (Vignette): Женщина 68 лет обращается в поликлинику вместе с дочерью в связи с 4-месячным анамнезом постепенно нарастающей вялости (lethargy) и ухудшения памяти. Дочь обеспокоена тем, что мать перестала помнить, принимала ли она свои постоянные препараты. Дочь опасается, что матери может быть небезопасно жить одной. До того как 4 мес назад появились жалобы, женщина была очень занята общественной деятельностью, которую с тех пор прекратила, и дочь не замечала каких-либо нарушений памяти. Дочери не известно о каких-либо недавних заболеваниях или травмах. Обзор систем органов (Review of Systems): Общее состояние: Пациентка говорит, что постоянно чувствует усталость и обычно мёрзнет даже сейчас, летом. У неё плохой аппетит, однако за предшествующие 4 мес она прибавила 5 кг в весе, несмотря на сниженный аппетит. Лихорадки, озноба, головной боли или ломоты в теле нет. Кожа: Кожа стала сухой, волосы теперь жёсткие и редкие. Сыпи или зуда нет. Голова, глаза, уши, нос и горло (HEENT): Она отмечает чувство наполненности в горле, а дочь заметила, что голос матери стал охриплым, а лицо выглядит одутловатым, особенно вокруг глаз. Затруднения глотания нет. Дыхательная система: Пациентка сообщает о впервые возникшей одышке при нагрузке и необходимости останавливаться после подъёма на 1/2 лестничного пролёта. Кашля или свистящего дыхания нет. Сердечно-сосудистая система: Ранее у неё бывали эпизодические сердцебиения, но за последние 2 мес их не было. Отрицает боль в грудной клетке, ортопноэ (orthopnea) и пароксизмальную ночную одышку. Желудочно-кишечный тракт: Стул у пациентки урежился с ежедневного до одного раза в 3– 4 дня при использовании слабительных. Боли в животе и рвоты нет. Аппетит снижен. Мочеполовая система: Без особенностей Костно-мышечная система: Голеностопные суставы и голени отёчны больше, чем раньше. Она отмечает утомляемость и слабость в ногах при подъёме по лестнице или вставании со стула. Нервная система: Она стала медленнее выполнять повседневные действия, требуются дополнительные усилия. Дочь заметила, что мать с трудом вспоминает недавние события, например, принимала ли она свои препараты. Отрицает очаговую слабость или нарушения чувствительности, тремор и зрительные симптомы. Психический статус: Настроение подавленное, она часто остаётся в постели, не выходя из дома по многу дней. Анамнез заболеваний (Past Medical History): Медицинский анамнез: Артериальная гипертензия (hypertension), диагностированная 10 лет назад, контролируемая тремя антигипертензивными препаратами. Фибрилляция предсердий (ФП, atrial fibrillation, AF) с контролем частоты бисопрололом; предшествующая госпитализация с тахисистолической ФП, осложнённой острой левожелудочковой недостаточностью; кардиоверсия не восстановила синусовый ритм. Хирургический анамнез: Аппендэктомия (appendectomy) в возрасте 19 лет, операция по поводу синдрома запястного канала (carpal tunnel syndrome) слева 2 года назад. Препараты: Бисопролол 5 mg 1 раз/сут, рамиприл 10 mg 1 раз/сут, фуросемид 40 mg 1 раз/сут, варфарин 3 mg 1 раз/сут. Аллергии: Известных лекарственных аллергий нет. Семейный анамнез: У матери был гипотиреоз (hypothyroidism) и инсульт в возрасте старше 80 лет. Отец умер от метастатического рака толстой кишки. Социальный анамнез: Она питается здоровой сбалансированной пищей, единственная физическая активность — ходьба в ближайшие магазины дважды в неделю. Ранее работала администратором, но вышла на пенсию 3 года назад. Она не курит и употребляет алкоголь лишь эпизодически. За последние 3 года за границу не выезжала. Физикальное обследование (Physical Examination): Общий вид: Пациентка одета в несколько слоёв одежды, включая шерстяной свитер, несмотря на то что на улице 89° F. У неё маловыразительное выражение лица, она выглядит бледной и усталой. Витальные показатели: Температура: 35.8° C Пульс: 56 уд/мин, нерегулярный АД (blood pressure): 120/90 mm Hg Дыхание: 16/мин Кожа: Кожа прохладная и сухая, цианоза и сыпи нет. Волосы жёсткие и сухие с заметным выпадением волос в области бровей. Голова, глаза, уши, нос и горло: Периорбитальный отёк. Щитовидная железа незначительно увеличена с обеих сторон, плотная, безболезненная. Шейной лимфаденопатии нет. Дыхательная система: Хорошее проведение воздуха на вдохе и выдохе с единичными мелкопузырчатыми конечно-инспираторными хрипами в базальных отделах с обеих сторон, свистящих хрипов нет. Сердечно-сосудистая система: Неритмично-неправильный сердечный ритм с частотой 56 уд/мин, шумов, шума трения и ритма галопа нет. Пульсация яремных вен видна, но не повышена. Отёк 2+ обеих нижних конечностей. Пульс на тыльной артерии стопы (a. dorsalis pedis) пальпируется с трудом из-за отёка ног. Желудочно-кишечный тракт: Виден рубец после ранее выполненной аппендэктомии. Живот мягкий; отмечается умеренный дискомфорт в левой подвздошной области при нормальных кишечных шумах. При ректальном исследовании в прямой кишке определяется твёрдый кал коричневого цвета. Анализ кала на скрытую кровь отрицательный. Мочеполовая система: Без особенностей Костно-мышечная система: Имеется рубец на левом запястье после хирургической декомпрессии по поводу синдрома запястного канала. Симптом Тинеля (Tinel's sign) положительный справа. Нервная система: Движения и речь пациентки замедлены, но чёткие, тремора нет. Черепные нервы II–XII интактны. Отмечается проксимальная слабость (4+/5) обеих нижних конечностей, в остальном сила и мышечный тонус нормальные и симметричные; глубокие сухожильные рефлексы в целом снижены с удлинённой фазой расслабления. Подошвенные рефлексы с обеих сторон направлены вниз. Психический статус: Пациентка сообщает о сниженном настроении, но без суицидальных мыслей. Результаты исследований (Test Results): Результаты соответствующего обследования получены и показывают следующее: Тиреотропный гормон (ТТГ (thyroid-stimulating hormone), thyroid-stimulating hormone, TSH): 88 microIU/mL Тироксин свободный (T4): 0.4 ng/dL Трийодтиронин свободный (T3): 0.8 pg/mL Натрий: 135 mEq/L Калий: 4.3 mEq/L Азот мочевины крови (BUN): 8 mg/dL Креатинин: 0.9 mg/dL Гемоглобин: 9.8 g/dL Лейкоциты: 6,700/mcL Тромбоциты 159,000/mcL Средний объём эритроцита (MCV) 88 fL Средняя концентрация гемоглобина в эритроците (MCHC) 34 g/dL Рентгенография органов грудной клетки: Небольшое количество жидкости в правой междолевой щели, умеренные базальные дисковидные ателектазы с обеих сторон, увеличение размеров сердца. КТ (computed tomography) головы: Норма Приведены результаты ЭКГ (electrocardiogram). Результаты соответствующего обследования получены и показывают следующее: Исследование (единицы) Результат Антитела к тиреопероксидазе (ТПО (thyroid peroxidase), thyroid peroxidase, TPO) в сыворотке 258 IU/mL | C6: Тиреоидит Хашимото (Hashimoto thyroiditis) | D6: Требуется неэкстренная помощь | E6: Эндокринология (Endocrinology) | F6: пожилой возраст (>60) | G6: Возраст: 68 Пол: Женский Жалобы: Прогрессирующая вялость, непереносимость холода, прибавка массы тела несмотря на плохой аппетит, когнитивное снижение с провалами в памяти, охриплость голоса, периорбитальный отёк, одышка при нагрузке, отёк нижних конечностей, запор и генерализованная слабость на протяжении последних 4 месяцев. Анализ: У пациентки имеются классические признаки тяжёлого гипотиреоза (непереносимость холода, сухие жёсткие волосы, сухость кожи, охриплость, периорбитальный отёк, запор, проксимальная мышечная слабость, замедленная фаза расслабления глубоких сухожильных рефлексов) вместе с лабораторным подтверждением первичной недостаточности щитовидной железы (ТТГ (thyroid-stimulating hormone) 88 мкМЕ/мл, свободный Т4 0,4 нг/дл, свободный Т3 0,8 пг/мл) и положительными антителами к ТПО (thyroid peroxidase) (258 МЕ/мл), что соответствует аутоиммунному тиреоидиту Хашимото. Отягощающие факторы, повышающие срочность, включают: - Гипотермию (35,8 °C) - Брадикардию с неправильно нерегулярным ритмом (56 уд/мин) на фоне фибрилляции предсердий и предшествующей госпитализации по поводу сердечной недостаточности - Двусторонние базальные хрипы, умеренную кардиомегалию и рентгенологические признаки жидкости на рентгенограмме органов грудной клетки (CXR), указывающие на перегрузку объёмом/возможный выпот - Отёки, анемию (Hb 9,8 г/дл, нормоцитарная), лёгкую гипонатриемию (Na 135 мЭкв/л) - Когнитивные нарушения и депрессивные черты, вероятно вторичные по отношению к гипотиреозу («микседематозное безумие») Ключевые дифференциальные диагнозы для рассмотрения и исключения: вторичный (центральный) гипотиреоз, лекарственно‑индуцированный гипотиреоз, большое депрессивное расстройство/псевдодеменция, ранняя нейродегенеративная деменция, декомпенсированная сердечная недостаточность, анемия хронического заболевания, электролитные нарушения и надпочечниковая недостаточность. Учитывая сочетание тяжёлого гипотиреоза, гипотермии, брадикардии и признаков сердечной недостаточности, пациентка имеет высокий риск прогрессирования до микседематозной комы и поэтому нуждается в экстренной стационарной помощи с тщательным мониторингом. Необходимое диагностическое оборудование/исследования: - Утренний кортизол сыворотки (со стимуляционной пробой с АКТГ (adrenocorticotropic hormone), если кортизол пограничный) - Расширенная метаболическая панель (включая повторное определение натрия, калия, глюкозы) - Липидный профиль - Исследования обмена железа, витамин B12, фолат, уровни витамина D - Антитела к тиреоглобулину (по желанию) - Трансторакальная эхокардиография (оценка функции желудочков, перикардиального/плеврального выпота) - Ультразвуковое исследование грудной клетки (при подозрении на выпот) - ЭКГ (electrocardiogram) в 12 отведениях с телеметрическим мониторингом - Исходный INR (мониторинг варфарина) - Оценка старческой астении/функционального статуса (скорость ходьбы, оценка ADL/IADL) - Повторный общий анализ крови с исследованием железа/B12/фолата - Денситометрия костей (по желанию, не экстренно) Заключение: У пациентки тяжёлый первичный гипотиреоз вследствие тиреоидита Хашимото с множественными настораживающими признаками (гипотермия, брадикардия, признаки сердечной недостаточности, анемия, гипонатриемия, когнитивное снижение), которые ставят её под непосредственный риск микседематозной комы. Показана немедленная госпитализация для начала заместительной терапии тиреоидными гормонами под наблюдением и всестороннего обследования. Тип неотложности: Требуется экстренная помощь Субклиническая специализация: Эндокринология Рекомендации: 1. **Госпитализировать в отделение с мониторингом** (палата промежуточной интенсивности или ОРИТ (intensive care unit) по потребности) для непрерывного кардиального, температурного и неврологического мониторинга. 2. **Определить кортизол сыворотки** до введения любых тиреоидных гормонов; если кортизол < 5 мкг/дл, начать стрессовые дозы гидрокортизона в/в (100 мг каждые 8 ч) до левотироксина. 3. **Начать низкодозовый левотироксин** 25 мкг внутрь ежедневно (рассмотреть 12,5 мкг при старческой астении) и титровать каждые 4–6 недель на основании ТТГ (thyroid-stimulating hormone)/свободного Т4 и клинического ответа. 4. **Тщательно контролировать состояние сердца:** телеметрия для выявления брадиаритмий, повторная ЭКГ (electrocardiogram) ежедневно, коррекция дозы бисопролола по мере улучшения частоты сердечных сокращений и выполнение трансторакальной эхокардиографии в течение 24 ч. 5. **Ведение варфарина:** определить исходный INR; повторять INR ежедневно в течение первой недели после начала левотироксина и соответственно корректировать дозу варфарина (тиреоидный гормон может усиливать метаболизм). 6. **Лечить гипонатриемию** консервативно (ограничение жидкости при наличии симптомов) и контролировать натрий ежедневно. 7. **Устранить анемию:** выполнить полные исследования железа, B12, фолата; лечить выявленные дефициты; рассмотреть эритропоэтин, если анемия хронического заболевания сохраняется после коррекции тиреоидного статуса. 8. **Купировать запор** с помощью размягчителей стула, осмотических слабительных и увеличения пищевых волокон; ежедневно переоценивать характер стула. 9. **Назначить липидный профиль, витамин D, антитела к тиреоглобулину** для исходной оценки и последующего мониторинга. 10. **Провести оценку старческой астении и функционального статуса**; привлечь гериатров для планирования выписки, оценки безопасности домашней среды (риск падений, организация приёма лекарств) и обучения ухаживающих лиц. 11. **Обучение пациентки и ухаживающих лиц:** подчеркнуть постепенность улучшения симптомов, важность приверженности лечению, меры согревания и признаки ухудшения (нарастание вялости, усугубление гипотермии, боль в груди, одышка). 12. **План наблюдения:** - Повторить ТТГ (thyroid-stimulating hormone) и свободный Т4 через 6–8 недель; скорректировать дозу левотироксина. - Повторить общий анализ крови, электролиты, липидный профиль и INR (еженедельно в течение первого месяца, затем по стандарту). - Повторить эхокардиографию и ЭКГ (electrocardiogram) после коррекции дозы. - Амбулаторный визит к эндокринологу каждые 4–6 недель до достижения эутиреоза, затем каждые 6–12 месяцев. - Постоянное гериатрическое наблюдение/наблюдение первичного звена по поводу функционального статуса, скрининга депрессии и здоровья костей. Примечания: Нет. | H6: Возраст: 68 лет Пол: Женский Жалобы: Прогрессирующая вялость (lethargy), снижение памяти, непереносимость холода, прибавка массы тела несмотря на плохой аппетит, сухость кожи, охриплый голос, периорбитальный отёк, запоры, отёчность ног, одышка при нагрузке и подавленное настроение на протяжении 4 месяцев. Анализ: У пациентки классическая совокупность гипотиреоидных симптомов и признаков: утомляемость, непереносимость холода, прибавка массы тела, сухая жёсткая кожа и волосы, охриплость, периорбитальный отёк, брадикардия, запоры, отёки нижних конечностей, проксимальная мышечная слабость, замедленная фаза расслабления глубоких сухожильных рефлексов и когнитивное замедление. Лабораторные данные подтверждают первичный гипотиреоз (hypothyroidism): выраженно повышенный ТТГ (thyroid-stimulating hormone) (88 µIU/mL), низкий свободный T4 (0.4 ng/dL), низкий свободный T3 (0.8 pg/mL) и положительные антитела к ТПО (thyroid peroxidase) (258 IU/mL), что соответствует тиреоидиту Хашимото (Hashimoto’s thyroiditis). Дополнительные отклонения включают лёгкую гипонатриемию (Na 135 mEq/L), нормоцитарную анемию (Hb 9.8 g/dL, MCV 88 fL) и признаки перегрузки объёмом (базальные хрипы с обеих сторон, отёки ног, рентгенография органов грудной клетки с небольшим плевральным выпотом и увеличенным сердцем), вероятно связанные с обусловленной гипотиреозом кардиальной дисфункцией, наслоившейся на существовавшую ранее фибрилляцию предсердий и перенесённую сердечную недостаточность. Дифференциальные диагнозы включают депрессию, деменцию, сердечную недостаточность и анемию, однако гипотиреоз является объединяющим диагнозом, объясняющим все находки. Необходимое диагностическое оборудование/исследования: Нет (все необходимые исследования выполнены; требуется оценка ЭКГ (electrocardiogram), но дополнительного оборудования на данном этапе не требуется). Заключение: Первичный гипотиреоз (тиреоидит Хашимото) с сопутствующей нормоцитарной анемией, лёгкой гипонатриемией и признаками усугубления сердечной недостаточности на фоне известной фибрилляции предсердий и перенесённой сердечной недостаточности. Тип неотложности: Требуется неэкстренная помощь Субклиническая специализация: Эндокринология Рекомендации: Начать заместительную терапию левотироксином с низкой стартовой дозы (например, 25–50 mcg в сутки) с медленной титрацией с учётом возраста пациентки и кардиологического анамнеза. Контролировать ТТГ (thyroid-stimulating hormone) и свободный T4 каждые 4–6 недель и соответственно корректировать дозу. До начала терапии тиреоидными гормонами рассмотреть обследование на надпочечниковую недостаточность (например, утренний кортизол), чтобы не спровоцировать надпочечниковый криз, хотя явных признаков нет. Ведение сердечной недостаточности: продолжить фуросемид, контролировать вес, электролиты и функцию почек; корректировать диуретики по потребности. Провести дообследование по поводу анемии (обмен железа, B12, фолат), если она не объясняется одним лишь гипотиреозом. Продолжить варфарин с тщательным контролем МНО (international normalized ratio), поскольку заместительная терапия тиреоидными гормонами может изменять чувствительность к варфарину. Обеспечить обучение приверженности приёму препаратов (использование таблетницы или напоминаний) и привлечь семью. Направить к эндокринологу и кардиологу для координированного ведения. Примечания: Осторожность при применении левотироксина у пожилых пациентов с заболеванием сердца — начинать с низкой дозы и титровать медленно. Хотя у пациентки имеются гипотермия и брадикардия, микседематозной комы нет; при ухудшении психического статуса или развитии гемодинамической нестабильности требуется экстренная помощь. | I6: Возраст: 68 Пол: Женский Жалобы: Женщина 68 лет обращается с 4-месячным анамнезом прогрессирующей вялости (lethargy), снижения памяти, непереносимости холода, прибавки массы тела несмотря на плохой аппетит, запоров, охриплости, одутловатости лица, одышки при нагрузке, а также слабости и отёков нижних конечностей. Анализ: Клиническая картина в высокой степени соответствует тяжёлому первичному гипотиреозу (hypothyroidism). Ключевые находки включают утомляемость, когнитивное замедление, непереносимость холода, прибавку массы тела, сухость кожи, жёсткие волосы, периорбитальный отёк, охриплый голос, брадикардию, замедленные глубокие сухожильные рефлексы с удлинённой фазой расслабления, проксимальную мышечную слабость, запоры, анемию и гипонатриемию. Выраженно повышенный ТТГ (thyroid-stimulating hormone) (88 µIU/mL) и низкий свободный T4 (0.4 ng/dL) подтверждают первичный гипотиреоз. Положительные антитела к ТПО (thyroid peroxidase) указывают на аутоиммунный тиреоидит (тиреоидит Хашимото, Hashimoto’s thyroiditis) как вероятную этиологию. Фибрилляция предсердий, симптомы сердечной недостаточности (отёки, базальные хрипы с обеих сторон, кардиомегалия) и брадикардия у пациентки соответствуют сердечно-сосудистым эффектам гипотиреоза. Когнитивные и психиатрические симптомы (депрессия, вялость) часты при микседеме. Дифференциальные диагнозы, такие как депрессия, деменция, сердечная недостаточность или злокачественное новообразование, менее вероятны с учётом общей метаболической картины и однозначных лабораторных результатов. Необходимое диагностическое оборудование/исследования: Нет Заключение: У пациентки тяжёлый первичный гипотиреоз вследствие аутоиммунного тиреоидита, проявляющийся системными симптомами, включая когнитивные, сердечно-сосудистые, нервно-мышечные и метаболические нарушения. Тип неотложности: Требуется экстренная помощь Субклиническая специализация: Эндокринология Рекомендации: - Начать заместительную терапию левотироксином в подходящей дозе с осторожной титрацией ввиду сопутствующего сердечно-сосудистого заболевания (фибрилляция предсердий, перенесённая сердечная недостаточность). Рекомендуется сниженная стартовая доза (например, 25–50 mcg/сут) с постепенным повышением. - Тщательно контролировать состояние сердца; координировать ведение с кардиологом с учётом анамнеза фибрилляции предсердий и сердечной недостаточности. - Отменить или скорректировать препараты, если они вносят вклад в брадикардию (например, доза бисопролола может потребовать коррекции по мере улучшения функции щитовидной железы). - Устранить анемию (вероятно, анемия хронических заболеваний или железодефицитная вследствие особенностей питания/нарушения всасывания); рассмотреть исследование обмена железа, уровня витамина B12 и фолата. - Оценить гипонатриемию, связанную с микседемой; контролировать уровень натрия на фоне лечения. - Оценить безопасность пациентки и её функциональные возможности; привлечь социального работника или гериатра для оценки условий проживания и потребностей в поддержке. - Обучить пациентку и её семью в отношении гипотиреоза, приверженности терапии и ожидаемого улучшения симптомов в течение недель. - Назначить контроль ТТГ (thyroid-stimulating hormone) и свободного T4 через 6–8 недель для коррекции дозы. Примечания: Несмотря на отсутствие явной микседематозной комы, тяжесть симптомов, брадикардия, гипотермия (35.8°C) и гипонатриемия оправдывают неотложное лечение и тщательное наблюдение из-за риска декомпенсации. | J6: Возраст: 68 Пол: Женский Жалобы: Прогрессирующая вялость (lethargy), нарушение памяти, непереносимость холода, прибавка массы тела, сухость кожи, жёсткие волосы, отёки и одышка на протяжении 4 месяцев. Анализ: - Лабораторный профиль показывает выраженно повышенный ТТГ (thyroid-stimulating hormone) (88 µIU/mL) при низком свободном T4 (0.4 ng/dL) и низком свободном T3 (0.8 pg/mL), что соответствует первичному гипотиреозу (hypothyroidism). - Положительные антитела к ТПО (thyroid peroxidase) (258 IU/mL) и незначительно увеличенная, плотная, безболезненная щитовидная железа указывают на аутоиммунный тиреоидит (Hashimoto). - Клинические признаки (непереносимость холода, сухие жёсткие волосы, периорбитальный отёк, неямочная одутловатость лица, замедленные речь и движения, брадикардия, гипотермия 35.8 °C, нормоцитарная анемия, картина по типу лёгкой гипонатриемии) классичны для тяжёлого гипотиреоза (микседемы). - Изменение психического статуса пациентки и гипотермия вызывают опасения в отношении надвигающегося микседематозного криза — угрожающего жизни неотложного состояния, требующего безотлагательного лечения, даже несмотря на то что она ещё не в коме. - Сопутствующая фибрилляция предсердий с контролем частоты бисопрололом, хроническая сердечная недостаточность (анамнез левожелудочковой недостаточности, базальные хрипы с обеих сторон, отёки нижних конечностей) и терапия варфарином повышают сердечно-сосудистый риск; заместительная терапия тиреоидными гормонами может спровоцировать аритмии и изменить метаболизм варфарина. - Дифференциально-диагностические соображения (например, депрессия, побочные эффекты препаратов, анемия хронических заболеваний) менее вероятны с учётом убедительных биохимических и физикальных данных о тяжёлом гипотиреозе. Необходимое диагностическое оборудование/исследования: - Кортизол сыворотки (исходный) и стимуляционная проба с АКТГ (adrenocorticotropic hormone) (для исключения надпочечниковой недостаточности до начала заместительной терапии тиреоидными гормонами). - Непрерывная кардиотелеметрия / повторная ЭКГ (electrocardiogram) (мониторинг брадиаритмии или усугубления ФП). - Прикроватная эхокардиография (оценка функции левого желудочка и волемического статуса). - Повторный базовый биохимический профиль, общий анализ крови и коагулограмма после начала терапии. - Контрольная тиреоидная панель (ТТГ (thyroid-stimulating hormone), свободный T4) через 1–2 недели для подбора дозы. Заключение: У пациентки тяжёлый первичный гипотиреоз (тиреоидит Хашимото) с клиническими признаками микседемы и надвигающегося микседематозного криза, отягощённый кардиальной коморбидностью (ФП, перенесённая левожелудочковая недостаточность) и анемией. Требуется немедленное стационарное ведение. Тип неотложности: Требуется экстренная помощь Субклиническая специализация: Эндокринология Рекомендации: 1. **Госпитализация** в отделение с мониторингом (палата промежуточной интенсивности или ОРИТ (intensive care unit) при ухудшении психического статуса). 2. **Заместительная терапия тиреоидными гормонами**: - Начать с внутривенного левотироксина в нагрузочной дозе 200–400 µg (с поправкой на возраст, заболевание сердца; рассмотреть 150 µg), затем 25–50 µg внутривенно ежедневно до клинической стабилизации пациентки, затем перевод на пероральный левотироксин (начальная доза 25–50 µg в сутки с последующим повышением). - Тщательно контролировать частоту сердечных сокращений, артериальное давление и ЭКГ (electrocardiogram); отменить или снизить дозу бисопролола при усугублении брадикардии. 3. **Оценить функцию надпочечников** до начала терапии тиреоидными гормонами: определить кортизол сыворотки; при уровне < 5 µg/dL или при клиническом подозрении вводить стресс-дозу гидрокортизона 100 mg внутривенно каждые 8 ч до исключения надпочечниковой недостаточности. 4. **Кардиоваскулярное ведение**: - Продолжить варфарин с тщательным контролем МНО (international normalized ratio) (левотироксин может повышать МНО (international normalized ratio)). - Оптимизировать диурез фуросемидом при перегрузке объёмом; повторно оценить функцию почек и электролиты. - Рассмотреть консультацию кардиолога по контролю частоты при ФП на фоне улучшения тиреоидного статуса. 5. **Поддерживающая терапия**: - Тёплое помещение, пассивное согревание (избегать быстрого наружного нагревания). - Лечить запор с помощью смягчающих стул средств и поощрять двигательную активность по переносимости. - Оценить анемию; рассмотреть исследование обмена железа, B12, фолата; в первую очередь лечить лежащий в основе гипотиреоз. 6. **Обучение пациентки и наблюдение**: - Объяснить пожизненную потребность в левотироксине, важность приверженности и регулярного контроля функции щитовидной железы. - Организовать амбулаторное наблюдение эндокринолога в течение 1–2 недель после выписки. - Обсудить риск падений и потребность в помощи при управлении приёмом препаратов дома; привлечь социальные службы для возможной организации помощи на дому. Примечания: Нет.
A7: 6 | B7: Виньетка: Г-жа L — 61-летняя женщина, обратившаяся с кашлем с отхождением жёлтой мокроты в течение 4 дней. Симптомы начались 4 дня назад с ринореи (rhinorrhea) и продуктивного кашля. Изначально в течение 2 дней была лихорадка до 101, но сейчас она разрешилась. На приёме витальные показатели в норме и физикальное обследование без особенностей. В остальном она здорова, за исключением повышенного холестерина, по поводу которого получает лечение аторвастатином. Лекарственной аллергии нет. | C7: Острый бронхит (Acute bronchitis) | D7: Достаточно самопомощи | E7: Пульмонология (Pulmonology) | F7: пожилой возраст (>60) | G7: Возраст: 61 Пол: Женский Жалобы: 4‑дневный анамнез продуктивного кашля с жёлтой мокротой, которому предшествовали ринорея и лихорадка, разрешившиеся к настоящему времени. Анализ: Клиническая картина у пациентки классическая для острого бронхита, наиболее вероятно вирусного происхождения. Подтверждающие факты включают: (1) продромальный период инфекции верхних дыхательных путей (ринорея) с последующим продуктивным кашлем, (2) лихорадку продолжительностью не более 2 дней, в настоящее время разрешившуюся, (3) нормальные показатели жизненно важных функций и отсутствие особенностей при аускультации лёгких и (4) отсутствие «красных флагов» (например, тахипноэ, гипоксии, боли в груди, кровохарканья, изменения психического статуса). Нормальные данные осмотра делают внебольничную пневмонию маловероятной, хотя возраст ≥ 60 лет умеренно повышает базовый риск; однако очаговых изменений или стойкой лихорадки, свидетельствующих в пользу пневмонии, нет. Дифференциальный диагноз включает вирусную инфекцию верхних дыхательных путей/острый бронхит (наиболее вероятно), внебольничную пневмонию, грипп, COVID‑19, коклюш (если кашель станет затяжным) и постназальный затёк. Текущие данные не указывают на бактериальную инфекцию, а жёлтая мокрота сама по себе не требует назначения антибиотиков. Необходимое диагностическое оборудование/исследования: Нет Заключение: Это неосложнённый случай острого вирусного бронхита у в целом здоровой 61‑летней женщины, требующий только симптоматического лечения и информирования о тревожных признаках. Тип неотложности: Требуется неэкстренная помощь Субклиническая специализация: Общая медицина Рекомендации: 1. **Поддерживающая терапия** – Рекомендовать достаточную гидратацию, отдых и приём жаропонижающих средств (например, ацетаминофена) при остаточной лихорадке или дискомфорте. Безрецептурные противокашлевые или отхаркивающие средства могут применяться по потребности. 2. **Безопасность лекарственной терапии** – Аторвастатин не взаимодействует с типичными средствами поддерживающей терапии; коррекция дозы не требуется. 3. **Информирование пациентки** – Проинструктировать пациентку незамедлительно обратиться за медицинской помощью при появлении любых «красных флагов»: новой или усиливающейся лихорадки, одышки, боли в груди, кровохарканья, тахипноэ, гипоксии (SpO₂ < 95 %), спутанности сознания или любых признаков сепсиса. 4. **Наблюдение** – Плановое повторное посещение не требуется при улучшении симптомов. Рекомендовать повторный визит, если кашель сохраняется более 10–14 дней или появляются новые симптомы. 5. **Учесть дополнительные аспекты** – - **Статус курения**: Не указан; при необходимости провести консультирование по отказу от курения. - **Анамнез вакцинации** (грипп, COVID‑19, пневмококковая инфекция): Не указан; рекомендовать актуальную вакцинацию согласно рекомендациям для соответствующего возраста. - **Недавние контакты** (поездки, контакты с больными): Не указаны; собрать анамнез при ухудшении симптомов. - **Сопутствующие заболевания** (сахарный диабет, иммуносупрессия, заболевания сердца): Не указаны; их наличие снизило бы порог для дальнейшего обследования. Примечания: Нет. | H7: Возраст: 61 Пол: Женский Жалобы: Четырёхдневный анамнез продуктивного кашля с жёлтой мокротой после инфекции верхних дыхательных путей; лихорадка разрешилась. Анализ: Клиническая картина наиболее соответствует острому неосложнённому бронхиту, чаще всего вирусной этиологии. Подтверждающие факты включают: недавнюю ринорею (rhinorrhea), кратковременную разрешившуюся лихорадку, нормальные витальные показатели и физикальное обследование без особенностей. Жёлтая мокрота сама по себе не указывает на бактериальную инфекцию при отсутствии системных признаков. Ключевые дифференциальные диагнозы, которые следует рассмотреть, — внебольничная пневмония, COVID-19, обострение бронхиальной астмы/ХОБЛ (chronic obstructive pulmonary disease) и коклюш; ни один из них не подтверждается текущими данными (нет лихорадки, тахипноэ, гипоксии, очаговых изменений в лёгких или известного хронического заболевания лёгких). Необходимое диагностическое оборудование/исследования: Нет Заключение: Острый вирусный бронхит, самоограничивающийся, без признаков пневмонии или иных осложнений. Тип неотложности: Достаточно самопомощи Субклиническая специализация: Пульмонология Рекомендации: - Разъяснить пациентке, что заболевание обычно является самоограничивающимся. - Симптоматическое лечение: увеличить приём жидкости, использовать увлажнённый воздух, рассмотреть безрецептурные (OTC) анальгетики/жаропонижающие (например, ацетаминофен) при остаточном дискомфорте и противокашлевые средства, если кашель беспокоит. - Рекомендовать воздержаться от рутинного назначения антибиотиков; назначать только при вероятности бактериальной пневмонии (новая лихорадка, одышка, очаговые изменения). - Проинструктировать пациентку обратиться за помощью при нарастании лихорадки, одышке, боли в грудной клетке или если кашель сохраняется более 3 недель. - Наблюдение не требуется, если симптомы не изменятся; для успокоения может быть предложен плановый контрольный визит к врачу первичного звена через 1–2 недели. Примечания: Нет | I7: Возраст: 61 Пол: Женский Жалобы: 4 дня кашля с отхождением жёлтой мокроты, с ринореей (rhinorrhea) и разрешившейся лихорадкой. Анализ: У пациентки острый продуктивный кашель, ринорея и лихорадка, которая разрешилась. Витальные показатели и физикальное обследование в норме. Жёлтая мокрота не обязательно указывает на бактериальную инфекцию и часто встречается при вирусном бронхите. Основные дифференциально-диагностические соображения включают острый бронхит, вирусную инфекцию верхних дыхательных путей и пневмонию (менее вероятна с учётом нормальных витальных показателей и осмотра). Тревожные признаки, такие как гипоксия, тахипноэ или очаговые изменения в лёгких, отсутствуют. Необходимое диагностическое оборудование/исследования: Нет Заключение: Вероятно, острый бронхит или вирусная инфекция верхних дыхательных путей; заболевание самоограничивающееся, и поддерживающая терапия целесообразна с учётом нормальных витальных показателей и осмотра. Тип неотложности: Достаточно самопомощи Субклиническая специализация: Общая медицина Рекомендации: Рекомендовать поддерживающую терапию, включая покой, адекватную гидратацию и жаропонижающие (например, ацетаминофен) при возобновлении лихорадки или дискомфорта. Разъяснить пациентке, что антибиотики рутинно не показаны при остром бронхите у в остальном здорового пациента. Рекомендовать повторное обращение или наблюдение при ухудшении симптомов, возобновлении лихорадки или появлении новых респираторных симптомов (например, одышки, боли в грудной клетке). Продолжить приём аторвастатина в назначенном режиме. Примечания: Жёлтая мокрота не подтверждает бактериальную инфекцию; избегать необоснованного применения антибиотиков. Нет | J7: Возраст: 61 Пол: Женский Жалобы: Анамнез продуктивного кашля с жёлтой мокротой в течение 4 дней, которому предшествовали ринорея (rhinorrhea) и лихорадка, с тех пор разрешившаяся. Анализ: У пациентки острое респираторное заболевание, характеризующееся продуктивным кашлем и изменённым цветом мокроты, изначально сопровождавшееся субфебрильной лихорадкой. Симптомы улучшились, в настоящее время витальные показатели в норме и физикальное обследование без особенностей. В остальном она здорова, с хорошо контролируемой хронической гиперлипидемией. Клиническое течение наиболее соответствует острому бронхиту, вероятно вирусной этиологии, с учётом самоограничивающейся лихорадки, отсутствия очаговых изменений при осмотре и системного улучшения. Дифференциально-диагностические соображения включают лёгкую внебольничную пневмонию или поствирусную бактериальную суперинфекцию, однако они менее вероятны при отсутствии стойкой лихорадки, тахикардии, тахипноэ или патологических изменений в лёгких. Необходимое диагностическое оборудование/исследования: Нет Заключение: Острый бронхит, вероятно вирусный, с разрешающимися симптомами и без признаков тяжёлого течения или осложнений. Тип неотложности: Достаточно самопомощи Субклиническая специализация: Общая медицина Рекомендации: Поддерживающая терапия с гидратацией, покоем и жаропонижающими по потребности. Антибиотики не показаны с учётом отсутствия данных за бактериальную инфекцию и улучшения симптомов. Наблюдать за ухудшением симптомов, таких как возобновление лихорадки, одышка, плевральная боль в грудной клетке или кровохарканье, что потребует повторной оценки. Продолжить приём аторвастатина для контроля холестерина. Примечания: Нет
A8: 7 | B8: Клиническая ситуация (Vignette): Женщина 66 лет обратилась с жалобами на прогрессирующее вздутие живота (abdominal distension) в течение 2 дней, диффузную схваткообразную боль в животе и неукротимую рвоту (intractable vomiting), которая стала желчной, а затем каловой (feculent). Газы не отходят, стула не было в течение 36 часов. Хирургический анамнез: открытая аппендэктомия (open appendectomy) 30 лет назад и тотальная абдоминальная гистерэктомия (total abdominal hysterectomy) 15 лет назад. При осмотре: признаки обезвоживания, состояние средней тяжести. Витальные показатели: T 37.8C, ЧСС (heart rate) 110, ЧД (respiratory rate) 20, АД (blood pressure) 108/68, SpO2 97%. Живот значительно вздут, при перкуссии тимпанит, выслушиваются высокие звонкие «переливающиеся» кишечные шумы (high-pitched tinkling bowel sounds). Диффузная болезненность, наибольшая в околопупочной области, с умеренным непроизвольным напряжением мышц (involuntary guarding). Лабораторные данные: лейкоциты (WBC) 14,800/mcL, мочевина крови (BUN) 42, креатинин 1.6, лактат 3.1 mmol/L. КТ (computed tomography) брюшной полости выявляет расширенные петли тонкой кишки до 5.2 cm с отчётливой зоной перехода (transition point) в правом нижнем квадранте, симптомом каловых масс в тонкой кишке (small bowel feces sign) и возможной конфигурацией замкнутой петли (closed-loop). | C8: Тонкокишечная непроходимость (Small bowel obstruction) | D8: Требуется экстренная помощь | E8: Общая хирургия (General Surgery) | F8: пожилой возраст (>60) | G8: Возраст: 66 Пол: Женский Жалобы: Прогрессирующее вздутие живота, диффузная схваткообразная боль в животе, неукротимая желчная и каловая рвота, а также 36 часов обстипации (отсутствие отхождения газов и стула). Анализ: У пациентки классические признаки механической тонкокишечной непроходимости (mechanical small bowel obstruction): каловая рвота (feculent vomiting), обстипация (obstipation), вздутие живота, тимпанит при перкуссии с высокими звонкими «переливающимися» кишечными шумами (high-pitched tinkling bowel sounds), а также КТ (computed tomography)-признаки расширенных петель тонкой кишки (до 5.2 cm) с отчётливой зоной перехода (transition point) в правом нижнем квадранте и симптомом каловых масс в тонкой кишке (small bowel feces sign). Перенесённые открытая аппендэктомия и тотальная абдоминальная гистерэктомия убедительно свидетельствуют в пользу непроходимости, вызванной спаечным тяжом. Возможная конфигурация замкнутой петли (closed-loop), повышенный лактат (3.1 mmol/L), лейкоцитоз (14,800/mcL), тахикардия (ЧСС (heart rate) 110) и признаки обезвоживания (BUN 42, креатинин 1.6) вызывают серьёзные опасения в отношении странгуляции (strangulation) и ишемии кишки, что представляет собой хирургическую неотложную ситуацию. Основные соображения дифференциального диагноза включают спаечную тонкокишечную непроходимость с замкнутой петлёй/странгуляцией, внутреннюю грыжу, заворот и обтурирующее злокачественное новообразование. Необходимое диагностическое оборудование/исследования: Экстренная консультация общего хирурга; повторные осмотры живота в динамике; повторные анализы (ОАК (complete blood count), лактат, электролиты, функция почек); установка назогастрального зонда; внутривенная инфузионная реанимация. (КТ (computed tomography) брюшной полости с контрастированием уже выполнена.) Заключение: Острая тонкокишечная непроходимость, вероятно спаечной этиологии, с высоким подозрением на конфигурацию замкнутой петли и угрожающую странгуляцию/ишемию, требующая неотложного хирургического вмешательства. Тип неотложности: Требуется экстренная помощь Субклиническая специализация: Общая хирургия (General Surgery) Рекомендации: Экстренная консультация общего хирурга и оценка показаний к неотложной эксплоративной лапаротомии/лапароскопии с учётом конфигурации замкнутой петли и повышенного лактата. Начать агрессивную внутривенную инфузионную реанимацию для коррекции обезвоживания и преренальной азотемии. Установить назогастральный зонд для декомпрессии и соблюдать режим NPO (ничего внутрь). Проводить повторные осмотры живота в динамике и повторные определения лактата/ОАК (complete blood count) для мониторинга нарастания ишемии. Скорректировать электролитные нарушения. Ввести периоперационные антибиотики широкого спектра. Не откладывать хирургическое вмешательство. Примечания: Каловая рвота, конфигурация замкнутой петли и повышенный лактат указывают на возможную ишемию/странгуляцию кишки; неотложное оперативное лечение обязательно. Нет. | H8: Возраст: 66 Пол: Женский Жалобы: Прогрессирующее вздутие живота, диффузная схваткообразная боль в животе, желчная/каловая рвота и обстипация в течение 36 часов. Анализ: У пациентки классические признаки острой тонкокишечной непроходимости (acute small‑bowel obstruction): вздутый, тимпанический живот; высокие звонкие «переливающиеся» кишечные шумы (high‑pitched tinkling bowel sounds); рвота, ставшая желчной и каловой; отсутствие отхождения газов и стула. КТ (computed tomography)‑визуализация подтверждает расширенные петли тонкой кишки с отчётливой зоной перехода (transition point) в правом нижнем квадранте, симптом каловых масс в тонкой кишке (small‑bowel feces sign) и возможную конфигурацию замкнутой петли (closed‑loop) — всё это убедительно свидетельствует о механической непроходимости, наиболее вероятно спаечной, учитывая перенесённые открытую аппендэктомию и гистерэктомию. Лабораторные отклонения (лейкоцитоз, повышенные BUN/креатинин, лактат 3.1 mmol/L) указывают на обезвоживание и раннюю ишемию, что вызывает опасения в отношении странгуляции. Ключевые дифференциальные диагнозы включают спаечную тонкокишечную непроходимость, внутреннюю грыжу, заворот или неопластическую стриктуру, однако данные визуализации и хирургический анамнез делают спаечную непроходимость с замкнутой петлёй ведущим диагнозом. Необходимое диагностическое оборудование/исследования: Нет Заключение: Острая механическая тонкокишечная непроходимость с вероятной конфигурацией замкнутой петли и ранними признаками ишемии у женщины 66 лет, требующая безотлагательного хирургического вмешательства. Тип неотложности: Требуется экстренная помощь Субклиническая специализация: Общая хирургия (General Surgery) Рекомендации: - Немедленный режим NPO (ничего внутрь) и установка назогастрального зонда для декомпрессии желудка. - Агрессивная внутривенная инфузионная реанимация (например, изотоническими кристаллоидами) для коррекции обезвоживания и поддержания перфузии; контроль диуреза. - Повторные определения электролитов и лактата в динамике; при показаниях — исследование газов артериальной крови. - Начать внутривенные антибиотики широкого спектра с охватом грамотрицательных и анаэробных микроорганизмов (например, пиперациллин‑тазобактам) в связи с подозрением на странгуляцию/ишемию. - Неотложная консультация хирурга для эксплоративной лапаротомии или лапароскопической оценки с возможной резекцией нежизнеспособной кишки. - Непрерывный гемодинамический мониторинг; рассмотреть госпитализацию в ОРИТ (intensive care unit) в послеоперационном периоде. - Документировать и отслеживать нарастание перитонита, рост лактата или гемодинамическую нестабильность, что потребует немедленного оперативного лечения. Примечания: Нет | I8: Возраст: 66 Пол: женщина Жалобы: Прогрессирующее вздутие живота, схваткообразная боль в животе, неукротимая желчная и каловая рвота, отсутствие отхождения газов и стула в течение 36 часов. Анализ: У пациентки клинические и радиологические находки, соответствующие тонкокишечной непроходимости (small bowel obstruction, SBO), вероятно обусловленной спайками после перенесённых операций на брюшной полости (аппендэктомия и гистерэктомия). Ключевые находки включают вздутие живота, высокие звонкие «переливающиеся» кишечные шумы (high-pitched tinkling bowel sounds), отсутствие отхождения газов, лейкоцитоз, повышенный лактат (3.1 mmol/L) и КТ (computed tomography) с расширенными петлями тонкой кишки с зоной перехода (transition point) в правом нижнем квадранте, симптомом каловых масс в тонкой кишке (small bowel feces sign) и возможной конфигурацией замкнутой петли (closed-loop). Наличие лихорадки, тахикардии, повышенных маркеров воспаления и метаболических нарушений указывает на развивающуюся ишемию кишки или странгуляцию, что особенно тревожно с учётом возможной непроходимости по типу замкнутой петли, являющейся хирургической неотложной ситуацией. Дифференциальный диагноз включает механическую тонкокишечную непроходимость (спайки, грыжа, опухоль), парез кишечника (ileus) и толстокишечную непроходимость, однако визуализация подтверждает тонкокишечную непроходимость с признаками, подозрительными на странгуляцию. Необходимое диагностическое оборудование/исследования: Нет Заключение: Это случай острой тонкокишечной непроходимости с визуализационными и лабораторными находками, указывающими на возможную непроходимость по типу замкнутой петли и раннюю ишемию кишки, требующий немедленной хирургической оценки. Тип неотложности: Требуется экстренная помощь Субклиническая специализация: Общая хирургия (General Surgery) Рекомендации: Немедленная консультация хирурга при подозрении на тонкокишечную непроходимость с признаками странгуляции. Начать реанимационные мероприятия с обеспечением внутривенного доступа катетером большого диаметра, агрессивным восполнением жидкости и коррекцией электролитных нарушений. Установить назогастральный зонд для декомпрессии. Контролировать диурез и динамику лактата. Не давать ничего внутрь. Подготовить к возможной экстренной лапаротомии с учётом конфигурации замкнутой петли и признаков ишемии. Избегать опиоидов, которые могут маскировать клиническое прогрессирование. Примечания: Тонкокишечная непроходимость по типу замкнутой петли является хирургической неотложной ситуацией с высоким риском быстрого прогрессирования до ишемии и перфорации кишки. Клиническое ухудшение может быть стремительным; критически важны тщательный мониторинг и раннее вмешательство. | J8: Возраст: 66 Пол: Женский Жалобы: Прогрессирующее вздутие живота, диффузная схваткообразная боль в животе, неукротимая рвота жёлчно-каловым содержимым и отсутствие отхождения газов и стула в течение 2–3 дней. Анализ: У пациентки классическая картина механической тонкокишечной непроходимости (small-bowel obstruction, SBO): недавнее начало колికообразной боли, рвота, прогрессировавшая до калового содержимого, отсутствие отхождения газов и стула, выраженное вздутие живота, тимпанический звук над животом и высокочастотные звенящие кишечные шумы. Обширные перенесённые операции на брюшной полости (открытая аппендэктомия, тотальная абдоминальная гистерэктомия) делают спаечную болезнь наиболее вероятной этиологией, хотя внутреннюю грыжу или новообразование исключить нельзя. КТ (computed tomography) показывает расширенные петли тонкой кишки до 5,2 см, отчётливую точку перехода в правом нижнем квадранте, симптом кишечных каловых масс в тонкой кишке (small-bowel feces sign) и возможную конфигурацию замкнутой петли — находки, подтверждающие механическую тонкокишечную непроходимость высокой степени и вызывающие непосредственное опасение странгуляции/ишемии. Системные признаки «красных флагов» включают тахикардию (ЧСС (heart rate) 110), лейкоцитоз (лейкоциты 14 800), повышенный лактат (3,1 ммоль/л), лёгкое непроизвольное напряжение мышц и преренальную азотемию (мочевина 42 мг/дл, креатинин 1,6 мг/дл). Они указывают на развивающуюся ишемию кишки, дегидратацию и раннюю системную воспалительную реакцию, что требует срочной хирургической оценки. Ключевые дифференциальные диагнозы, которые следует иметь в виду, — толстокишечная непроходимость, заворот толстой кишки, внутренняя грыжа, мезентериальная ишемия без непроходимости, паралитическая кишечная непроходимость и перфорация полого органа. Однако наличие чёткой точки перехода и симптома кишечных каловых масс в тонкой кишке убедительно свидетельствует в пользу механической тонкокишечной непроходимости, наиболее вероятно спаечной. Необходимое диагностическое оборудование/исследования: - КТ (computed tomography) брюшной полости и таза с контрастным усилением (если первичное исследование было бесконтрастным) для оценки накопления контраста стенкой кишки и её жизнеспособности. - Повторная лабораторная панель, включая лактат, электролиты, показатели функции почек и общий анализ крови, для мониторинга ухудшения. - Серийные осмотры живота (клиническая оценка у постели больного). Заключение: У пациентки острая тонкокишечная непроходимость высокой степени с возможной конфигурацией замкнутой петли и клиническими признаками угрожающей ишемии кишки, что представляет собой хирургическую неотложную ситуацию. Тип неотложности: Требуется экстренная помощь Субклиническая специализация: Общая хирургия Рекомендации: 1. **Немедленная реанимация** — начать активное восполнение объёма изотоническими растворами внутривенно (например, физиологический раствор или сбалансированный кристаллоид) для коррекции преренальной азотемии и поддержания перфузии; контролировать диурез. 2. **Режим NPO** — не давать пациентке ничего внутрь. 3. **Назогастральная декомпрессия** — установить назогастральный зонд для устранения растяжения желудка и снижения риска аспирации. 4. **Антибиотики широкого спектра** — начать эмпирическую терапию (например, пиперациллин-тазобактам или цефтриаксон + метронидазол) с учётом высокого подозрения на бактериальную транслокацию/раннюю перфорацию при непроходимости по типу замкнутой петли. 5. **Срочная консультация хирурга** — немедленно уведомить дежурную бригаду общей хирургии; без промедления подготовиться к возможному экстренному оперативному вмешательству (лапаротомия или лапароскопия). 6. **Визуализация** — выполнить КТ (computed tomography) брюшной полости/таза с контрастным усилением сейчас, если предыдущее сканирование проводилось без внутривенного контраста; если контраст противопоказан, направить в операционную исходя из клинической неотложности. 7. **Мониторинг** — проводить серийные осмотры живота, повторное измерение витальных показателей и лабораторные анализы (включая лактат) каждые 1–2 часа для выявления быстрого ухудшения. 8. **Периоперационные соображения** — учитывать возраст пациентки и имеющуюся почечную дисфункцию при выборе растворов, антибиотиков и анестетиков; рано привлечь анестезиолога для стратификации риска. Примечания: Нет.
A9: 8 | B9: Виньетка: 8-летний мальчик доставлен в отделение неотложной помощи после того, как примерно 45 минут назад стянул на себя с плиты кастрюлю с кипящей водой. Он получил ожоги кипятком (scald burns) передней поверхности грудной клетки, живота, обеих верхних конечностей и отдельных участков лица. Он безутешно плачет. Значимый анамнез отсутствует. При осмотре в сознании, но с выраженным болевым синдромом и дистрессом. Витальные показатели: T 36.6C, ЧСС (heart rate) 152, ЧД (respiratory rate) 28, АД (blood pressure) 94/58, SpO2 98%. Масса тела 28 kg. Ожоги охватывают примерно 20% общей площади поверхности тела: участки эритемы с крупными неповреждёнными и вскрывшимися пузырями (поверхностный частичный ожог, superficial partial thickness) на грудной клетке и животе, с восковидно-белыми нечувствительными участками (глубокий частичный до полнослойного, deep partial to full thickness) на обоих предплечьях. Циркулярных ожогов не выявлено. Ожоги лица поверхностные, без опаления волос в носовых ходах и без признаков ингаляционной травмы. Осиплости голоса или стридора нет. Рассчитана формула Parkland (20% TBSA x 28 kg x 4 mL = 2,240 mL раствора Рингера лактата (LR) за первые 24 часа), обеспечен внутривенный доступ, введён морфин для обезболивания. | C9: Тяжёлые ожоги (2-й/3-й степени) (Severe burns (2nd/3rd degree)) | D9: Требуется экстренная помощь | E9: Неотложная помощь (Emergency) | F9: дети (<15) | G9: Возраст: 8 Пол: Мужской Жалобы: Ожог кипятком (scald burn) с поражением передней поверхности грудной клетки, живота, обеих верхних конечностей и отдельных участков лица, полученный 45 минут назад, с выраженной болью и дистрессом. Анализ: Пациент — 8-летний мальчик со значительным ожогом кипятком, охватывающим примерно 20% общей площади поверхности тела (TBSA), включая глубокие частичные до полнослойных ожоги обоих предплечий и поверхностные частичные ожоги грудной клетки, живота и лица. Отмечаются тахикардия (ЧСС (heart rate) 152) и тахипноэ (ЧД (respiratory rate) 28), соответствующие раннему гиповолемическому шоку или болевой реакции, но гемодинамика стабильна (АД (blood pressure) 94/58). Признаков ингаляционной травмы нет (нет опаления волос в носовых ходах, осиплости, стридора или гипоксии). Боль выраженная, требует опиоидной анальгезии. Формула Parkland корректно применена для инфузионной терапии. Наличие нечувствительных восковидно-белых участков на предплечьях указывает на глубокое дермальное или полнослойное поражение, которое может потребовать хирургического вмешательства. Циркулярных ожогов нет, поэтому немедленных показаний к некротомии (escharotomy) нет. Дифференциальные соображения включают оценку тяжести ожога, риск инфекции, адекватность инфузионной терапии и обезболивание, но данных за ингаляционную травму или нарушение проходимости дыхательных путей нет. Необходимое диагностическое оборудование/исследования: Отсутствуют Заключение: 8-летний мальчик с ожогом кипятком 20% TBSA, преимущественно поверхностным и глубоким частичным, без нарушения проходимости дыхательных путей и ингаляционной травмы, нуждающийся в немедленной инфузионной терапии, обезболивании и направлении в ожоговый центр ввиду глубины и распространённости ожога. Тип неотложности: Требуется экстренная помощь Субклиническая специализация: Неотложная помощь Рекомендации: - Продолжить внутривенную инфузионную терапию раствором Рингера лактата: ввести половину объёма по Parkland (1,120 mL) в первые 8 часов после ожога (т. е. примерно 140 mL/час в течение ближайших ~8 часов), а остаток — за последующие 16 часов. - Поддерживать адекватную анальгезию внутривенным морфином или другими подходящими опиоидами; часто переоценивать боль. - Осторожно очищать раны с соблюдением стерильности; удалять вскрывшиеся пузыри, но рассмотреть сохранение неповреждённых пузырей. - Наносить местное антимикробное средство (например, сульфадиазин серебра или мупироцин на лицо) и неприлипающие повязки. - Отслеживать признаки перегрузки жидкостью или недостаточной инфузионной терапии (целевой диурез: 1 mL/kg/час у детей). - Обеспечить консультацию ожогового центра или перевод согласно критериям American Burn Association (ожог >10% TBSA у ребёнка, частичные ожоги значительных площадей, ожоги лица, кистей или гениталий, либо ожоги, требующие специализированной помощи). - Профилактика столбняка: ввести при отсутствии актуальной вакцинации. - Непрерывный контроль витальных показателей, уровня сознания и диуреза. - Избегать гипотермии: поддерживать тёплую среду и согревать внутривенные растворы. Примечания: Отсутствуют | H9: Возраст: 8 лет Пол: Мужской Жалобы: Ожоги кипятком (scald burns) передней поверхности грудной клетки, живота, обеих верхних конечностей и отдельных участков лица кипящей водой, с выраженной болью и дистрессом. Анализ: Пациент получил ожог кипятком 20% TBSA смешанной глубины: поверхностный частичный (эритема с неповреждёнными и вскрывшимися пузырями) на грудной клетке и животе и глубокий частичный до полнослойного (восковидно-белые нечувствительные участки) на обоих предплечьях. Циркулярных ожогов нет, опаления волос в носовых ходах нет, признаков ингаляционной травмы нет (нет осиплости или стридора). Витальные показатели демонстрируют тахикардию (ЧСС (heart rate) 152) и умеренную гипотензию (АД (blood pressure) 94/58), соответствующие боли и ранним перераспределениям жидкости. Рассчитана формула Parkland (4 mL x 20% TBSA x 28 kg = 2,240 mL LR за 24 часа), обеспечен внутривенный доступ и введён морфин. Дифференциальные соображения включают углубление ожога, развитие гиповолемического шока, инфекцию и компартмент-синдром (compartment syndrome) (хотя циркулярных ожогов нет). Необходимое диагностическое оборудование/исследования: Мочевой катетер для почасового контроля диуреза; непрерывный мониторинг витальных показателей; серийная оценка ожоговых ран; лабораторные исследования (ОАК (complete blood count), электролиты, функция почек) по клиническим показаниям. Заключение: 8-летний мальчик с ожогом кипятком 20% TBSA смешанной глубины, требующий экстренной ожоговой помощи, включая продолжение инфузионной терапии, обезболивание и обработку ран, без признаков ингаляционной травмы и циркулярных ожогов. Тип неотложности: Требуется экстренная помощь Субклиническая специализация: Неотложная помощь Рекомендации: Продолжить инфузионную терапию по формуле Parkland раствором Рингера лактата (2,240 mL за 24 часа, с введением половины в первые 8 часов от момента травмы). Тщательно контролировать диурез (цель 1-1.5 mL/kg/hr у детей) и витальные показатели. Продолжить морфин для обезболивания. Обеспечить адекватную обработку ожоговых ран (очищение, удаление вскрывшихся пузырей, нанесение местных антимикробных средств и стерильные повязки). Рассмотреть направление в специализированный ожоговый центр с учётом глубоких частичных до полнослойных ожогов обоих предплечий. Отслеживать признаки инфекции, углубления ожога и развития компартмент-синдрома. Периодически переоценивать состояние дыхательных путей несмотря на отсутствие текущих признаков ингаляционной травмы. Примечания: Отсутствие циркулярных ожогов и ингаляционной травмы — благоприятные находки; однако глубокие частичные до полнослойных ожоги предплечий требуют тщательного наблюдения на предмет прогрессирования и функциональных нарушений. | I9: Возраст: 8 лет Пол: Мужской Жалобы: Ожоги кипятком передней поверхности грудной клетки, живота, обеих верхних конечностей и лица после случайного пролития кипящей воды, с выраженной болью и дистрессом. Анализ: Ребёнок получил термические ожоги кипятком, охватывающие примерно 20 % общей площади поверхности тела (TBSA). Поверхностные ожоги неполной толщины кожи (эритема с неповреждёнными или вскрывшимися пузырями) затрагивают грудную клетку и живот, тогда как глубокие ожоги неполной и полной толщины кожи (восковидно-белые, нечувствительные) захватывают оба предплечья. Показатели жизненно важных функций (ЧСС (heart rate) 152 уд/мин, АД (blood pressure) 94/58 мм рт. ст.) указывают на компенсированный гиповолемический шок. Признаков ингаляционной травмы нет (ожоги лица поверхностные, отсутствуют опалённые волоски носа, охриплость или стридор). Циркулярных ожогов нет, поэтому некротомия (escharotomy) в настоящее время не показана. Распространённость (>10 % TBSA у ребёнка) и глубина ожогов соответствуют критериям экстренной инфузионной терапии, направления в ожоговый центр и мультидисциплинарного ведения. В дифференциальный ряд входят другие причины повреждения кожи (химический ожог, контактный ожог, синдром Стивенса — Джонсона) и неслучайная травма; однако описанный механизм соответствует случайному ожогу кипятком. Необходимое диагностическое оборудование/исследования: - Монитор непрерывного контроля жизненно важных показателей (ЧСС (heart rate), АД (blood pressure), ЧД (respiratory rate), SpO₂) - Катетер для контроля диуреза или устройство для сбора мочи для почасового измерения - Прикроватные анализы крови (point-of-care): общий анализ крови (CBC), электролиты, глюкоза, артериальные/венозные газы крови при клинической необходимости - Прикроватный офтальмологический осмотр (щелевая лампа) при поражении лица/глаз - Проверка прививочного статуса по столбняку (изучение документации или серология при неопределённости) Заключение: 8-летний мальчик с ожогами кипятком 20 % TBSA, включая глубокие ожоги обоих предплечий, находится в ранней стадии компенсированного шока и нуждается в немедленной, протокол-ориентированной инфузионной терапии, активном обезболивании, обработке ран и направлении в ожоговый центр. Ингаляционной травмы и циркулярных ожогов нет, но необходим тщательный мониторинг отёка дыхательных путей и компартмент-синдрома. Тип неотложности: Требуется экстренная помощь Субклиническая специализация: Педиатрия Рекомендации: 1. **Инфузионная терапия** – Начать введение раствора Рингера лактата по формуле Паркланда: 4 мл × 28 кг × 20 % TBSA = 2 240 мл за 24 ч. Первую половину (1 120 мл) ввести в течение первых 8 ч от момента ожога (≈ 7 ч осталось), корректируя скорость для поддержания диуреза ≥ 1 мл/кг/ч. 2. **Обезболивание** – Продолжить внутривенное введение морфина с титрованием до контроля боли; добавить вспомогательные средства, такие как инфузия кетамина, ацетаминофен и противорвотные препараты, по необходимости для мультимодального обезболивания. 3. **Обработка ран** – Аккуратно очистить ожоги, удалить вскрывшиеся пузыри и наложить местную антимикробную повязку (например, сульфадиазин серебра). Ежедневно повторно оценивать глубину; рассмотреть раннее иссечение и пересадку кожи при глубоких ожогах предплечий. 4. **Терморегуляция** – Поддерживать нормотермию с помощью тёплых одеял, контроля температуры окружающей среды и устройств активного согревания по необходимости. 5. **Профилактика столбняка** – Проверить прививочный статус; ввести бустерную дозу столбнячного анатоксина или противостолбнячный иммуноглобулин, если статус неизвестен или неполный. 6. **Направление в ожоговый центр** – Организовать немедленный перевод в детский ожоговый центр для окончательного лечения (критерии соблюдены: >10 % TBSA, глубокие ожоги, поражение лица). 7. **Консультации специалистов** – - Ожоговая хирургия/пластическая хирургия для планирования операции. - Детская интенсивная терапия для продолжения противошоковой терапии и мониторинга. - Офтальмология для оценки поражения лица/глаз. - Психиатрия/психология или специалист по детской психосоциальной поддержке (child-life specialist) для помощи при травме. 8. **Мониторинг** – Непрерывный кардиомониторинг и пульсоксиметрия, почасовой диурез, серийная оценка жизненно важных показателей и частая оценка признаков компартмент-синдрома или нарастающего отёка дыхательных путей. Получить исходные лабораторные показатели (общий анализ крови (CBC), электролиты, глюкоза, газы артериальной крови (ABG)) и повторять по клиническим показаниям. 9. **Питание** – Начать раннее энтеральное питание для удовлетворения возросших метаболических потребностей. 10. **Обучение семьи и маршрутизация** – Предоставить лицам, осуществляющим уход, информацию об уходе за ожогами, признаках инфекции, контроле водного баланса и последующих визитах. Обеспечить психосоциальную поддержку и рассмотреть любые опасения относительно возможной неслучайной травмы. Примечания: Нет | J9: Возраст: 8 лет Пол: Мужской Жалобы: Ожоги кипятком (scald burns) передней поверхности грудной клетки, живота, обеих верхних конечностей и лица после пролития кипящей воды (~45 мин назад) Анализ: Пациент получил термическую травму с поражением ~20 % общей площади поверхности тела (TBSA). Поверхностный частичный ожог (эритема с пузырями) присутствует на грудной клетке и животе, тогда как глубокие частичные и полнослойные (восковидно-белые, нечувствительные) участки затрагивают оба предплечья. Циркулярных ожогов и ингаляционной травмы не выявлено, дыхательные пути проходимы. Витальные показатели демонстрируют тахикардию (ЧСС (heart rate) 152), вероятно вследствие боли и ранней гиповолемии. У детей ожоги >10 % TBSA требуют безотлагательной инфузионной терапии, анальгезии, профилактики столбняка и специализированной ожоговой помощи. Формула Parkland (2 240 mL LR/24 h) предписывает введение половины расчётного объёма в первые 8 h от момента травмы; следовательно, показаны активная инфузионная терапия, контроль диуреза и раннее лечение ожоговых ран. Дифференциально-диагностические соображения (например, скрытая ингаляционная травма, инфекция) маловероятны с учётом отсутствия опаления волос лица, осиплости, стридора и циркулярных ожогов, но требуют постоянной переоценки. Необходимое диагностическое оборудование/исследования: - Базовая лабораторная панель: ОАК (complete blood count), базовая метаболическая панель (BMP), коагулограмма, лактат сыворотки, группа крови и скрининг - Контроль диуреза (катетер или катетер Фолея) - Непрерывный кардиомониторинг и пульсоксиметрия - Рентгенография органов грудной клетки — только при изменении респираторного статуса Заключение: 8-летний ребёнок с ожогами кипятком 20 % TBSA, включая глубокие частичные повреждения предплечий, нуждается в экстренной инфузионной терапии, обезболивании, профилактике столбняка и специализированном лечении ожоговых ран с привлечением детской ожоговой бригады. Тип неотложности: Требуется экстренная помощь Субклиническая специализация: Педиатрия Рекомендации: 1. **Инфузионная терапия** – Начать инфузию раствора Рингера лактата в объёме 1120 mL в течение ближайших ~7,5 h (корректировать для поддержания диуреза ≥ 1 mL/kg/h). 2. **Анальгезия** – Продолжить внутривенный морфин; рассмотреть адъюванты (например, инфузию кетамина) при выраженной боли. 3. **Профилактика столбняка** – Ввести бустерную дозу столбнячного анатоксина, если прививочный статус неизвестен или прошло >5 лет с последней дозы; ввести противостолбнячный иммуноглобулин при загрязнённой ране и неопределённом прививочном статусе. 4. **Обработка ожоговых ран** – Осторожно очистить стерильным физиологическим раствором, нанести местное антимикробное средство (например, сульфадиазин серебра или мафенида ацетат) и неприлипающие повязки. Защитить участки глубокого частичного ожога предплечий; рассмотреть раннее направление в детский ожоговый центр для возможного иссечения/пересадки кожи. 5. **Мониторинг** – Непрерывный контроль витальных показателей, сердечного ритма, пульсоксиметрия; почасовой диурез; повторные анализы каждые 6-8 h для коррекции инфузионной терапии. 6. **Наблюдение за дыхательными путями** – Отслеживать отсроченную ингаляционную травму; быть готовым к респираторной поддержке при развитии отёка. 7. **Иммобилизация** – Шинировать предплечья в функциональном положении для профилактики контрактур. 8. **Психологическая поддержка** – Обеспечить успокоение с учётом возраста; привлечь специалистов по сопровождению детей (child life services). 9. **Консультации** – Детская ожоговая хирургия, детская интенсивная терапия и служба лечения боли. Примечания: Отсутствуют.
A10: 9 | B10: Виньетка: Мальчик 5 лет доставлен матерью, которая заметила множественные зудящие красные бугорки на его руках и ногах после того, как он провёл вторую половину дня, играя на улице во дворе. Бугорки появились в течение последних 24 часов. Он расчёсывает их, но мать сообщает об отсутствии значимого отёка за пределами непосредственной зоны каждого бугорка. Отрицает лихорадку, боли в суставах и недавние поездки. При осмотре выявляется примерно 8–10 мелких эритематозных папул (erythematous papules) диаметром 3–5 мм каждая, рассеянных по обоим предплечьям и голеням. У нескольких из них имеются мелкие центральные точечные отверстия (central puncta). Окружающей флегмоны (cellulitis), лимфангита (lymphangitis) и регионарной лимфаденопатии (lymphadenopathy) нет. | C10: Укусы комаров (mosquito bites) без аллергии | D10: Достаточно самопомощи | E10: Дерматология (Dermatology) | F10: дети (<15) | G10: Возраст: 5 Пол: Мужской Жалобы: Множественные зудящие красные бугорки на руках и ногах, появившиеся в течение последних 24 часов после игр на улице. Анализ: Клиническая картина соответствует укусам насекомых, что подтверждается острым появлением мелких эритематозных папул (erythematous papules) с центральными точечными отверстиями (central puncta), зудом и указанием на недавнее пребывание на улице. Высыпания локализованы на открытых участках кожи (предплечья и голени), при этом нет данных за системные симптомы (например, лихорадку, боли в суставах), значимый отёк, инфекцию (нет флегмоны (cellulitis), лимфангита (lymphangitis) или лимфаденопатии (lymphadenopathy)) либо уртикарные признаки. Основные дифференциальные диагнозы включают аллергический контактный дерматит, папулёзную крапивницу (papular urticaria) (часто вследствие укусов насекомых) и, менее вероятно, вирусную экзантему или раннюю стадию болезни Лайма (хотя мигрирующая эритема и укус клеща в анамнезе не отмечены). Наличие центральных точечных отверстий убедительно свидетельствует в пользу реакции на укус членистоногого. Необходимое диагностическое оборудование/исследования: Нет Заключение: Острая папулёзная крапивница, вероятно вследствие укусов насекомых после пребывания на улице, без признаков вторичной инфекции или системного вовлечения. Тип неотложности: Достаточно самопомощи Субклиническая специализация: Дерматология Рекомендации: Рекомендовать симптоматическое лечение, включая холодные компрессы, местные противозудные средства (например, лосьон каламин или местный кортикостероид низкой активности, такой как крем 1% гидрокортизона) и пероральные антигистаминные препараты (например, цетиризин или лоратадин) от зуда. Проконсультировать о необходимости избегать расчёсывания для предотвращения вторичной бактериальной инфекции. Рекомендовать защитную одежду и репеллент от насекомых при будущих прогулках на улице. Наблюдать за признаками инфекции (усиление покраснения, локальный жар, боль, гной) или системными симптомами, которые потребуют повторной оценки. Примечания: Нет | H10: Возраст: 5 лет Пол: Мужской Жалобы: Зудящие красные папулы на предплечьях и голенях, появившиеся после игр на улице. Анализ: У ребёнка выявляются 8‑10 мелких (3‑5 мм) эритематозных папул с центральной точкой (puncta) на открытых участках кожи, возникших в течение 24 ч после пребывания на улице, без системных симптомов (лихорадка, боль в суставах) и без признаков инфекции (флегмона (cellulitis), лимфангит (lymphangitis), лимфаденопатия). Эти данные классичны для папулёзной крапивницы (papular urticaria), вызванной укусами насекомых (комары, блохи, краснотелковые клещи и др.). Распределение на предплечьях и голенях, недавняя активность на улице и отсутствие чесоточных ходов или элементов в кожных складках помогают отличить это состояние от чесотки (scabies). Основные дифференциальные диагнозы, которые следует рассмотреть: контактный дерматит, чесотка, фолликулит, вирусная экзантема, острая крапивница, импетиго, лекарственная сыпь, ранняя многоформная эритема и ранний лаймский боррелиоз (Lyme disease). Тревожные признаки («красные флаги»), которые указывали бы на более серьёзное состояние, включают лихорадку, распространяющуюся эритему, боль, несоразмерную проявлениям, регионарную лимфаденопатию, флегмону (cellulitis)/лимфангит, буллы, признаки системной инфекции или анафилаксию. Необходимое диагностическое оборудование/исследования: Нет Заключение: Клиническая картина наиболее соответствует папулёзной крапивнице вследствие укусов насекомых — состоянию кожи низкой срочности, неэкстренному, которое может вестись в педиатрической первичной помощи. Тип неотложности: Требуется неэкстренная помощь Субклиническая специализация: Педиатрия Рекомендации: 1. **Симптоматическая терапия** – назначить соответствующую возрасту дозу перорального антигистаминного препарата второго поколения (например, цетиризин 5 мг один раз в сутки) и наносить топический кортикостероид низкой активности (например, 1% гидрокортизон) на поражённые участки 2‑3 раза в день. 2. **Поддерживающий уход** – прохладные компрессы на каждый элемент, коротко подстригать ногти, объяснить ребёнку не расчёсывать, чтобы снизить риск вторичной бактериальной инфекции (импетиго). 3. **Профилактическое обучение** – - Использовать репеллент от насекомых, содержащий ДЭТА (DEET) или пикаридин, при нахождении на улице. - Носить защитную одежду (длинные рукава, брюки) в периоды пиковой активности насекомых. - Проверять домашних животных на наличие блох или клещей и при необходимости проводить лечение. - Выполнять осмотр на предмет клещей после пребывания на улице; помнить о местных клещевых инфекциях даже без поездок. - Избегать новых сортов мыла, моющих средств или топических продуктов, которые могут спровоцировать контактный дерматит. - Следить за тревожными признаками (лихорадка, распространяющееся покраснение, отёк, боль, лимфаденопатия, буллы, дыхательная недостаточность) и незамедлительно обращаться за помощью при их появлении. 4. **Наблюдение** – плановый повторный осмотр через 3‑5 дней для оценки ответа; более ранний визит при ухудшении высыпаний или появлении системных симптомов. Рассмотреть направление к дерматологу, если высыпания сохраняются более 2 недель, становятся атипичными или при подозрении на рецидивирующую папулёзную крапивницу. Примечания: Нет | I10: Возраст: 5 лет Пол: Мужской Жалобы: Множественные зудящие красные бугорки на руках и ногах, появившиеся в течение последних 24 часов после игр на улице во дворе. Анализ: Клиническая картина множественных мелких (3-5 мм) эритематозных папул (erythematous papules) с центральными точечными отверстиями (central puncta), распределённых на открытых участках (оба предплечья и голени) и появившихся после игр на улице, весьма характерна для укусов насекомых (папулёзная крапивница, papular urticaria). Центральные точечные отверстия представляют собой места укусов. Отсутствие лихорадки, болей в суставах, значимого отёка, флегмоны (cellulitis), лимфангита (lymphangitis) и регионарной лимфаденопатии (lymphadenopathy) свидетельствует против системной инфекции или более серьёзного процесса в мягких тканях. Дифференциальный диагноз включает контактный дерматит (менее вероятен с учётом точечных отверстий и распределения), крапивницу (обычно проявляется более крупными волдырями без точечных отверстий) и чесотку (обычно поражает межпальцевые промежутки и характеризуется наличием ходов, не ограничиваясь открытыми участками). Данные анамнеза и осмотра наиболее убедительно поддерживают доброкачественную реакцию на укусы насекомых. Необходимое диагностическое оборудование/исследования: Нет (клинический диагноз; лабораторные или визуализирующие исследования в настоящее время не показаны) Заключение: Доброкачественная реакция на укусы насекомых (папулёзная крапивница) у мальчика 5 лет, самоограничивающаяся, без признаков вторичной инфекции или системного вовлечения. Тип неотложности: Достаточно самопомощи Субклиническая специализация: Дерматология Рекомендации: 1. Успокоить мать, объяснив, что это распространённая самоограничивающаяся реакция на укусы насекомых, которая обычно разрешается в течение 1-2 недель. 2. Симптоматическое лечение: прикладывать прохладные компрессы к поражённым участкам для уменьшения зуда; использовать безрецептурный пероральный антигистаминный препарат (например, цетиризин или дифенгидрамин) в дозировке, соответствующей возрасту 5 лет, для контроля зуда. 3. Местная терапия: наносить лосьон каламин или местный кортикостероид низкой активности (например, гидрокортизон 1%) на отдельные папулы дважды в сутки в течение нескольких дней для уменьшения воспаления и зуда. 4. Рекомендовать матери не допускать расчёсывания: коротко стричь и содержать в чистоте ногти ребёнка для минимизации повреждения кожи и снижения риска вторичной бактериальной инфекции. 5. Профилактические меры: использовать репеллент от насекомых и подходящую одежду (длинные рукава и брюки) при играх на улице в травянистой или лесистой местности. 6. Наблюдение за настораживающими признаками: проинструктировать мать обратиться для осмотра, если бугорки станут всё более болезненными, красными, горячими или гнойными (признаки вторичной инфекции), либо если у ребёнка появятся лихорадка, распространяющееся покраснение или отёк за пределами мест укусов. Примечания: Нет | J10: Возраст: 5 лет Пол: Мужской Жалобы: Зудящие красные папулёзные бугорки на предплечьях и голенях после игр на улице. Анализ: У ребёнка выявляются множественные мелкие (3‑5 мм) эритематозные папулы (erythematous papules) с центральными точечными отверстиями (central puncta), ограниченные открытыми участками, без отёка, лихорадки, болей в суставах, флегмоны (cellulitis), лимфангита (lymphangitis) или лимфаденопатии (lymphadenopathy). Острое начало после пребывания на улице настоятельно указывает на реакцию гиперчувствительности к укусам насекомых (папулёзная крапивница, papular urticaria). В дифференциальный диагноз входят вирусная экзантема, обострение атопического дерматита, контактный дерматит, чесотка и раннее импетиго; они менее вероятны с учётом распределения высыпаний, отсутствия системных признаков и характерных центральных точечных отверстий. Необходимое диагностическое оборудование/исследования: Нет Заключение: Доброкачественная папулёзная крапивница, вероятно вследствие укусов насекомых; данных за инфекцию или системное вовлечение нет. Тип неотложности: Требуется неэкстренная помощь Субклиническая специализация: Педиатрия Рекомендации: - Обеспечить симптоматическое облегчение: пероральный антигистаминный препарат (например, цетиризин 5 mg один раз в сутки) и/или местный кортикостероид низкой активности (например, 1% гидрокортизон) на поражённые участки дважды в сутки. - Рекомендовать прохладные компрессы и коротко стричь ногти для минимизации экскориаций. - Проинформировать ухаживающего о необходимости избегать дальнейшего контакта с насекомыми (использовать репеллент, носить длинные рукава/брюки на улице). - Наблюдать за признаками вторичной инфекции (усиление покраснения, локальное повышение температуры, гной, лихорадка) и обратиться для осмотра при их появлении. - Повторный осмотр через 3–5 дней или раньше при ухудшении. Примечания: Нет
